{
  "header": {
    "title": "Event Details: 74191912-a8c6-4729-b4d1-b8c4087305e8",
    "generated_time": "2025-12-10T23:38:13.171165431Z",
    "url": "/affiliates/v1/racing/events/74191912-a8c6-4729-b4d1-b8c4087305e8?enc=json&include_form=true&include_odds=true&include_flucs=true&include_speedmap=true&include_past_performances=true&include_form_indicators=true&include_jockey_stats=true&include_trainer_stats=true"
  },
  "params": {
    "enc": "json",
    "id": "74191912-a8c6-4729-b4d1-b8c4087305e8",
    "present_overlay": false,
    "with_big_bets": false,
    "with_live_bets": false,
    "with_money_tracker": false,
    "with_biggest_bet": false,
    "will_pays": false,
    "with_tote_trends_data": false,
    "bet_type_filter": "",
    "bets_limit": 10
  },
  "data": {
    "race": {
      "event_id": "74191912-a8c6-4729-b4d1-b8c4087305e8",
      "meeting_name": "Q Straight",
      "display_meeting_name": "Q Straight",
      "meeting_id": "c39221d6-dd33-4a25-b9bf-7d7ffce03929",
      "status": "Open",
      "description": "Ladbrokes Quick Multi",
      "advertised_start": 1765418040,
      "actual_start": 1765418040,
      "advertised_start_string": "2025-12-11 01:54:00 +0000 UTC",
      "actual_start_string": "2025-12-11 01:54:00 +0000 UTC",
      "race_number": 3,
      "type": "G",
      "start_type": "",
      "country": "AUS",
      "state": "QLD",
      "distance": 350,
      "weather": "Fine",
      "form_guide": "",
      "comment": "EQUITY (6) box seated early before forging to the lead turning and lifting to score (21.97) at Q Lakeside in a Maiden over 390m. Shapes as a top winning chance on latest effort. LORNETT SWIFT (1) turned in a solid run last start over 520m at Q Parklands finishing 4th and beaten only 4.5 lengths (30.80). The form from her last run stacks up well. Should be in this for a long way. DAD'S VISION (7) produced a moderate performance last time when seventh at this track over 350m behind Barry The Boss (19.57) in a Grade 6. Was in the money prior to that. Form from his last run is proving very strong. In the mix. I'M THE PROBLEM (4) will have admirers again after placing at this track and distance last time out.",
      "silk_base_url": "drr38safykj6s.cloudfront.net",
      "track_condition": "Good",
      "track_direction": "Left",
      "silk_url": "https://www.ladbrokes.com.au/images/sprites/greyhound-silks-standard.png",
      "entrant_count": 8,
      "positions_paid": 3,
      "video_channels": [
        "Live1"
      ],
      "video_channels_meta": {
        "Live1": {
          "RaceNo": 3,
          "RaceType": "G",
          "SlotType": "",
          "SlotTitle": "",
          "VenueName": "Q Straight",
          "CrossPoint": 21,
          "RacePriority": "2",
          "SlotDuration": "",
          "SchedulerNote": "P1 (Metropolitan)",
          "CrossPointName": "SKY 02",
          "SlotDescription": "",
          "UtcRaceStartTime": "2025-12-11T01:54:00Z",
          "VenueCountryCode": "AU",
          "VenueProviderName": "SKY",
          "DisplayRaceStartTime": "2025-12-11T11:54:00",
          "SchedulerNotePriority": "None"
        }
      },
      "tips": [
        "9d95e1f7-154f-483e-92d6-50cbc6bbafa4",
        "bf13941c-ed00-4fad-ad2d-04cde06168fd",
        "dbe1f8ed-7326-40e1-88cc-f46bb2b122c8",
        "47a7321a-bc31-4a66-97bb-58d9d5afe69c"
      ],
      "rail_position": "",
      "group": "",
      "prize_monies": {
        "1st": 1755,
        "2nd": 540,
        "3rd": 270,
        "4th": 135,
        "total_value": 0
      },
      "track_home_straight": 0
    },
    "favourite": {
      "entrant_id": "9d95e1f7-154f-483e-92d6-50cbc6bbafa4",
      "market_name": "Final Field",
      "primary_market": true,
      "name": "Equity",
      "is_scratched": false,
      "gear": "",
      "best_time": "NBT",
      "odds": {
        "fixed_win": 1.7,
        "fixed_place": 1.1
      },
      "scratch_time": 0,
      "barrier": 6,
      "runner_number": 6,
      "prize_money": "1950",
      "age": 1,
      "sex": "B",
      "colour": "BL",
      "silk_colours": "",
      "silk_url_64x64": "",
      "silk_url_128x128": "",
      "form_comment": null,
      "class_level": "",
      "jockey": "",
      "apprentice_indicator": "",
      "allowance_weight": "",
      "owners": "Craig Chandler",
      "country": "AUS",
      "trainer_name": "Craig Chandler",
      "last_twenty_starts": "1",
      "sire": "ASTON RUPEE (AUS)",
      "dam": "MAYORESS (AUS)",
      "breeding": "b ASTON RUPEE (AUS)-MAYORESS (AUS)",
      "weight": {
        "allocated": "",
        "total": ""
      },
      "favourite": false,
      "mover": false,
      "speedmap": {
        "settling_lengths": 4,
        "entrant_id": "9d95e1f7-154f-483e-92d6-50cbc6bbafa4"
      },
      "form_indicators": null,
      "past_performances": null,
      "jockey_past_performances": null,
      "trainer_location": "Buccan"
    },
    "runners": [
      {
        "entrant_id": "bf13941c-ed00-4fad-ad2d-04cde06168fd",
        "market_name": "Final Field",
        "primary_market": true,
        "name": "Lornett Swift",
        "is_scratched": false,
        "gear": "",
        "best_time": "19.67",
        "odds": {
          "fixed_win": 18,
          "fixed_place": 2.5
        },
        "scratch_time": 0,
        "barrier": 1,
        "runner_number": 1,
        "prize_money": "6875",
        "age": 2,
        "sex": "B",
        "colour": "BDL",
        "silk_colours": "",
        "silk_url_64x64": "",
        "silk_url_128x128": "",
        "form_comment": null,
        "class_level": "",
        "jockey": "",
        "apprentice_indicator": "",
        "allowance_weight": "",
        "owners": "Dean Clarson",
        "country": "AUS",
        "trainer_name": "Dean Clarson",
        "last_twenty_starts": "6834852564",
        "sire": "ASTON RUPEE (AUS)",
        "dam": "FRENCH VANILLA (AUS)",
        "breeding": "b ASTON RUPEE (AUS)-FRENCH VANILLA (AUS)",
        "weight": {
          "allocated": "",
          "total": ""
        },
        "favourite": false,
        "mover": false,
        "speedmap": {
          "settling_lengths": 1,
          "entrant_id": "bf13941c-ed00-4fad-ad2d-04cde06168fd",
          "label": "Back Marker"
        },
        "form_indicators": null,
        "past_performances": null,
        "jockey_past_performances": null,
        "trainer_location": "Ellangowan",
        "meta": null,
        "flucs": [
          41,
          31,
          21,
          20,
          19,
          18
        ],
        "scr_time": null,
        "competitor_id": "",
        "ride_guide_exists": false,
        "ride_guide_thumbnail": "",
        "ride_guide_file": "",
        "flucs_with_timestamp": {
          "last_six": [
            {
              "timestamp": "2025-12-10T22:33:36.714538804Z",
              "fluc": 41
            },
            {
              "timestamp": "2025-12-10T22:35:57.010686256Z",
              "fluc": 31
            },
            {
              "timestamp": "2025-12-10T22:37:06.703832819Z",
              "fluc": 21
            },
            {
              "timestamp": "2025-12-10T22:41:06.129480472Z",
              "fluc": 20
            },
            {
              "timestamp": "2025-12-10T22:42:30.121510361Z",
              "fluc": 19
            },
            {
              "timestamp": "2025-12-10T23:01:36.006652179Z",
              "fluc": 18
            }
          ],
          "open": {
            "timestamp": "2025-12-10T22:03:39.103409982Z",
            "fluc": 26
          },
          "high": {
            "timestamp": "2025-12-10T22:33:36.714538804Z",
            "fluc": 41
          },
          "low": {
            "timestamp": "2025-12-10T23:01:36.006652179Z",
            "fluc": 18
          },
          "nine_am": {
            "timestamp": "0001-01-01T00:00:00Z",
            "fluc": 0
          }
        }
      },
      {
        "entrant_id": "04a1c10f-fc1d-4e02-9fa2-eaff50aa938a",
        "market_name": "Final Field",
        "primary_market": true,
        "name": "Scotty's Idea",
        "is_scratched": false,
        "gear": "",
        "best_time": "19.60",
        "odds": {
          "fixed_win": 12,
          "fixed_place": 2.15
        },
        "scratch_time": 0,
        "barrier": 2,
        "runner_number": 2,
        "prize_money": "2250",
        "age": 2,
        "sex": "B",
        "colour": "W/BL",
        "silk_colours": "",
        "silk_url_64x64": "",
        "silk_url_128x128": "",
        "form_comment": null,
        "class_level": "",
        "jockey": "",
        "apprentice_indicator": "",
        "allowance_weight": "",
        "owners": "Steven Scott",
        "country": "AUS",
        "trainer_name": "John Quarman",
        "last_twenty_starts": "7566777566",
        "sire": "FERDINAND BOY (AUS)",
        "dam": "SOME IDEA (AUS)",
        "breeding": "b FERDINAND BOY (AUS)-SOME IDEA (AUS)",
        "weight": {
          "allocated": "",
          "total": ""
        },
        "favourite": false,
        "mover": false,
        "speedmap": {
          "settling_lengths": 3,
          "entrant_id": "04a1c10f-fc1d-4e02-9fa2-eaff50aa938a",
          "label": "Midfield"
        },
        "form_indicators": null,
        "past_performances": null,
        "jockey_past_performances": null,
        "trainer_location": "Elimbah",
        "meta": null,
        "flucs": [
          23,
          26,
          18,
          14,
          13,
          12
        ],
        "scr_time": null,
        "competitor_id": "",
        "ride_guide_exists": false,
        "ride_guide_thumbnail": "",
        "ride_guide_file": "",
        "flucs_with_timestamp": {
          "last_six": [
            {
              "timestamp": "2025-12-10T22:25:49.802137854Z",
              "fluc": 23
            },
            {
              "timestamp": "2025-12-10T22:28:36.402736092Z",
              "fluc": 26
            },
            {
              "timestamp": "2025-12-10T22:32:40.757285399Z",
              "fluc": 18
            },
            {
              "timestamp": "2025-12-10T22:33:36.714552133Z",
              "fluc": 14
            },
            {
              "timestamp": "2025-12-10T22:35:28.707611463Z",
              "fluc": 13
            },
            {
              "timestamp": "2025-12-10T23:02:05.410725908Z",
              "fluc": 12
            }
          ],
          "open": {
            "timestamp": "2025-12-10T22:03:39.103381451Z",
            "fluc": 19
          },
          "high": {
            "timestamp": "2025-12-10T22:28:36.402736092Z",
            "fluc": 26
          },
          "low": {
            "timestamp": "2025-12-10T23:02:05.410725908Z",
            "fluc": 12
          },
          "nine_am": {
            "timestamp": "0001-01-01T00:00:00Z",
            "fluc": 0
          }
        }
      },
      {
        "entrant_id": "792911af-dbc1-4d92-bbb3-51cb8a7d2d16",
        "market_name": "Final Field",
        "primary_market": true,
        "name": "She's Dynamite",
        "is_scratched": false,
        "gear": "",
        "best_time": "20.01",
        "odds": {
          "fixed_win": 35,
          "fixed_place": 3.4
        },
        "scratch_time": 0,
        "barrier": 3,
        "runner_number": 3,
        "prize_money": "3060",
        "age": 2,
        "sex": "B",
        "colour": "BL",
        "silk_colours": "",
        "silk_url_64x64": "",
        "silk_url_128x128": "",
        "form_comment": null,
        "class_level": "",
        "jockey": "",
        "apprentice_indicator": "",
        "allowance_weight": "",
        "owners": "Tanya Snow",
        "country": "AUS",
        "trainer_name": "Ned Snow",
        "last_twenty_starts": "82635755x8",
        "sire": "SUPERIOR PANAMA (USA)",
        "dam": "BLUE CARAT (AUS)",
        "breeding": "b SUPERIOR PANAMA (USA)-BLUE CARAT (AUS)",
        "weight": {
          "allocated": "",
          "total": ""
        },
        "favourite": false,
        "mover": false,
        "speedmap": {
          "settling_lengths": 2,
          "entrant_id": "792911af-dbc1-4d92-bbb3-51cb8a7d2d16",
          "label": "Midfield"
        },
        "form_indicators": null,
        "past_performances": null,
        "jockey_past_performances": null,
        "trainer_location": "Purga",
        "meta": null,
        "flucs": [
          81,
          91,
          101,
          71,
          41,
          35
        ],
        "scr_time": null,
        "competitor_id": "",
        "ride_guide_exists": false,
        "ride_guide_thumbnail": "",
        "ride_guide_file": "",
        "flucs_with_timestamp": {
          "last_six": [
            {
              "timestamp": "2025-12-10T22:49:43.402472457Z",
              "fluc": 81
            },
            {
              "timestamp": "2025-12-10T23:01:36.006766831Z",
              "fluc": 91
            },
            {
              "timestamp": "2025-12-10T23:02:05.410698845Z",
              "fluc": 101
            },
            {
              "timestamp": "2025-12-10T23:04:44.756587969Z",
              "fluc": 71
            },
            {
              "timestamp": "2025-12-10T23:05:36.801570075Z",
              "fluc": 41
            },
            {
              "timestamp": "2025-12-10T23:33:48.004872521Z",
              "fluc": 35
            }
          ],
          "open": {
            "timestamp": "2025-12-10T22:03:39.103440558Z",
            "fluc": 23
          },
          "high": {
            "timestamp": "2025-12-10T23:02:05.410698845Z",
            "fluc": 101
          },
          "low": {
            "timestamp": "2025-12-10T22:03:39.103440558Z",
            "fluc": 23
          },
          "nine_am": {
            "timestamp": "0001-01-01T00:00:00Z",
            "fluc": 0
          }
        }
      },
      {
        "entrant_id": "47a7321a-bc31-4a66-97bb-58d9d5afe69c",
        "market_name": "Final Field",
        "primary_market": true,
        "name": "I'm The Problem",
        "is_scratched": false,
        "gear": "",
        "best_time": "19.47",
        "odds": {
          "fixed_win": 3.2,
          "fixed_place": 1.28
        },
        "scratch_time": 0,
        "barrier": 4,
        "runner_number": 4,
        "prize_money": "2025",
        "age": 1,
        "sex": "D",
        "colour": "BL",
        "silk_colours": "",
        "silk_url_64x64": "",
        "silk_url_128x128": "",
        "form_comment": null,
        "class_level": "",
        "jockey": "",
        "apprentice_indicator": "",
        "allowance_weight": "",
        "owners": "Casey Dargusch",
        "country": "AUS",
        "trainer_name": "Bailey Dargusch",
        "last_twenty_starts": "13",
        "sire": "HOOKED ON SCOTCH (AUS)",
        "dam": "CAGE TO RATTLE (AUS)",
        "breeding": "d HOOKED ON SCOTCH (AUS)-CAGE TO RATTLE (AUS)",
        "weight": {
          "allocated": "",
          "total": ""
        },
        "favourite": false,
        "mover": false,
        "speedmap": {
          "settling_lengths": 7,
          "entrant_id": "47a7321a-bc31-4a66-97bb-58d9d5afe69c",
          "label": "Midfield"
        },
        "form_indicators": null,
        "past_performances": null,
        "jockey_past_performances": null,
        "trainer_location": "Churchable",
        "meta": null,
        "flucs": [
          2.7,
          2.8,
          2.9,
          3,
          3.1,
          3.2
        ],
        "scr_time": null,
        "competitor_id": "",
        "ride_guide_exists": false,
        "ride_guide_thumbnail": "",
        "ride_guide_file": "",
        "flucs_with_timestamp": {
          "last_six": [
            {
              "timestamp": "2025-12-10T22:35:28.70762859Z",
              "fluc": 2.7
            },
            {
              "timestamp": "2025-12-10T22:38:13.903999586Z",
              "fluc": 2.8
            },
            {
              "timestamp": "2025-12-10T22:49:07.004031307Z",
              "fluc": 2.9
            },
            {
              "timestamp": "2025-12-10T22:51:10.210616569Z",
              "fluc": 3
            },
            {
              "timestamp": "2025-12-10T23:01:36.006556377Z",
              "fluc": 3.1
            },
            {
              "timestamp": "2025-12-10T23:05:02.55539687Z",
              "fluc": 3.2
            }
          ],
          "open": {
            "timestamp": "2025-12-10T22:03:39.103368338Z",
            "fluc": 2.3
          },
          "high": {
            "timestamp": "2025-12-10T23:05:02.55539687Z",
            "fluc": 3.2
          },
          "low": {
            "timestamp": "2025-12-10T22:03:39.103368338Z",
            "fluc": 2.3
          },
          "nine_am": {
            "timestamp": "0001-01-01T00:00:00Z",
            "fluc": 0
          }
        }
      },
      {
        "entrant_id": "ab332cb6-891c-4484-9997-0f1893db268e",
        "market_name": "Final Field",
        "primary_market": true,
        "name": "Blazing Bronco",
        "is_scratched": false,
        "gear": "",
        "best_time": "19.41",
        "odds": {
          "fixed_win": 71,
          "fixed_place": 4.5
        },
        "scratch_time": 0,
        "barrier": 5,
        "runner_number": 5,
        "prize_money": "5440",
        "age": 3,
        "sex": "D",
        "colour": "BDL",
        "silk_colours": "",
        "silk_url_64x64": "",
        "silk_url_128x128": "",
        "form_comment": null,
        "class_level": "",
        "jockey": "",
        "apprentice_indicator": "",
        "allowance_weight": "",
        "owners": "Renald Attard",
        "country": "AUS",
        "trainer_name": "Renald Attard",
        "last_twenty_starts": "5356746266",
        "sire": "MY REDEEMER (AUS)",
        "dam": "BELVEDERE BABE (AUS)",
        "breeding": "d MY REDEEMER (AUS)-BELVEDERE BABE (AUS)",
        "weight": {
          "allocated": "",
          "total": ""
        },
        "favourite": false,
        "mover": false,
        "speedmap": {
          "settling_lengths": 3,
          "entrant_id": "ab332cb6-891c-4484-9997-0f1893db268e",
          "label": "Midfield"
        },
        "form_indicators": null,
        "past_performances": null,
        "jockey_past_performances": null,
        "trainer_location": "Fairney View",
        "meta": null,
        "flucs": [
          41,
          46,
          51,
          61,
          67,
          71
        ],
        "scr_time": null,
        "competitor_id": "",
        "ride_guide_exists": false,
        "ride_guide_thumbnail": "",
        "ride_guide_file": "",
        "flucs_with_timestamp": {
          "last_six": [
            {
              "timestamp": "2025-12-10T22:25:49.802107518Z",
              "fluc": 41
            },
            {
              "timestamp": "2025-12-10T22:33:36.714527032Z",
              "fluc": 46
            },
            {
              "timestamp": "2025-12-10T22:34:48.802430457Z",
              "fluc": 51
            },
            {
              "timestamp": "2025-12-10T22:41:06.129427565Z",
              "fluc": 61
            },
            {
              "timestamp": "2025-12-10T22:49:07.004120973Z",
              "fluc": 67
            },
            {
              "timestamp": "2025-12-10T22:49:43.402484058Z",
              "fluc": 71
            }
          ],
          "open": {
            "timestamp": "2025-12-10T22:03:39.103369661Z",
            "fluc": 31
          },
          "high": {
            "timestamp": "2025-12-10T22:49:43.402484058Z",
            "fluc": 71
          },
          "low": {
            "timestamp": "2025-12-10T22:03:39.103369661Z",
            "fluc": 31
          },
          "nine_am": {
            "timestamp": "0001-01-01T00:00:00Z",
            "fluc": 0
          }
        }
      },
      {
        "entrant_id": "9d95e1f7-154f-483e-92d6-50cbc6bbafa4",
        "market_name": "Final Field",
        "primary_market": true,
        "name": "Equity",
        "is_scratched": false,
        "gear": "",
        "best_time": "NBT",
        "odds": {
          "fixed_win": 1.7,
          "fixed_place": 1.1
        },
        "scratch_time": 0,
        "barrier": 6,
        "runner_number": 6,
        "prize_money": "1950",
        "age": 1,
        "sex": "B",
        "colour": "BL",
        "silk_colours": "",
        "silk_url_64x64": "",
        "silk_url_128x128": "",
        "form_comment": null,
        "class_level": "",
        "jockey": "",
        "apprentice_indicator": "",
        "allowance_weight": "",
        "owners": "Craig Chandler",
        "country": "AUS",
        "trainer_name": "Craig Chandler",
        "last_twenty_starts": "1",
        "sire": "ASTON RUPEE (AUS)",
        "dam": "MAYORESS (AUS)",
        "breeding": "b ASTON RUPEE (AUS)-MAYORESS (AUS)",
        "weight": {
          "allocated": "",
          "total": ""
        },
        "favourite": true,
        "mover": false,
        "speedmap": {
          "settling_lengths": 4,
          "entrant_id": "9d95e1f7-154f-483e-92d6-50cbc6bbafa4",
          "label": "Midfield"
        },
        "form_indicators": null,
        "past_performances": null,
        "jockey_past_performances": null,
        "trainer_location": "Buccan",
        "meta": null,
        "flucs": [
          1.75,
          1.7,
          1.75,
          1.7,
          1.65,
          1.7
        ],
        "scr_time": null,
        "competitor_id": "",
        "ride_guide_exists": false,
        "ride_guide_thumbnail": "",
        "ride_guide_file": "",
        "flucs_with_timestamp": {
          "last_six": [
            {
              "timestamp": "2025-12-10T22:34:48.802490368Z",
              "fluc": 1.75
            },
            {
              "timestamp": "2025-12-10T22:35:28.70764009Z",
              "fluc": 1.7
            },
            {
              "timestamp": "2025-12-10T22:36:50.602699213Z",
              "fluc": 1.75
            },
            {
              "timestamp": "2025-12-10T22:41:06.129455012Z",
              "fluc": 1.7
            },
            {
              "timestamp": "2025-12-10T23:02:49.507637916Z",
              "fluc": 1.65
            },
            {
              "timestamp": "2025-12-10T23:04:17.003098274Z",
              "fluc": 1.7
            }
          ],
          "open": {
            "timestamp": "2025-12-10T22:03:39.103426966Z",
            "fluc": 1.7
          },
          "high": {
            "timestamp": "2025-12-10T22:36:50.602699213Z",
            "fluc": 1.75
          },
          "low": {
            "timestamp": "2025-12-10T23:02:49.507637916Z",
            "fluc": 1.65
          },
          "nine_am": {
            "timestamp": "0001-01-01T00:00:00Z",
            "fluc": 0
          }
        }
      },
      {
        "entrant_id": "dbe1f8ed-7326-40e1-88cc-f46bb2b122c8",
        "market_name": "Final Field",
        "primary_market": true,
        "name": "Dad's Vision",
        "is_scratched": false,
        "gear": "",
        "best_time": "19.50",
        "odds": {
          "fixed_win": 4.5,
          "fixed_place": 1.45
        },
        "scratch_time": 0,
        "barrier": 7,
        "runner_number": 7,
        "prize_money": "3260",
        "age": 3,
        "sex": "D",
        "colour": "BL",
        "silk_colours": "",
        "silk_url_64x64": "",
        "silk_url_128x128": "",
        "form_comment": null,
        "class_level": "",
        "jockey": "",
        "apprentice_indicator": "",
        "allowance_weight": "",
        "owners": "Peter Young",
        "country": "AUS",
        "trainer_name": "Peter Young",
        "last_twenty_starts": "178x37",
        "sire": "MEPUNGA BLAZER (AUS)",
        "dam": "SUTTON'S LASS (AUS)",
        "breeding": "d MEPUNGA BLAZER (AUS)-SUTTON'S LASS (AUS)",
        "weight": {
          "allocated": "",
          "total": ""
        },
        "favourite": false,
        "mover": true,
        "speedmap": {
          "settling_lengths": 8,
          "entrant_id": "dbe1f8ed-7326-40e1-88cc-f46bb2b122c8",
          "label": "Front Runner"
        },
        "form_indicators": null,
        "past_performances": null,
        "jockey_past_performances": null,
        "trainer_location": "Prenzlau",
        "meta": null,
        "flucs": [
          4.6,
          4.5,
          4.6,
          4.5,
          4.6,
          4.5
        ],
        "scr_time": null,
        "competitor_id": "",
        "ride_guide_exists": false,
        "ride_guide_thumbnail": "",
        "ride_guide_file": "",
        "flucs_with_timestamp": {
          "last_six": [
            {
              "timestamp": "2025-12-10T22:52:38.409644751Z",
              "fluc": 4.6
            },
            {
              "timestamp": "2025-12-10T22:54:47.904991308Z",
              "fluc": 4.5
            },
            {
              "timestamp": "2025-12-10T22:56:58.111174639Z",
              "fluc": 4.6
            },
            {
              "timestamp": "2025-12-10T23:01:36.006528717Z",
              "fluc": 4.5
            },
            {
              "timestamp": "2025-12-10T23:24:36.400777737Z",
              "fluc": 4.6
            },
            {
              "timestamp": "2025-12-10T23:33:48.00470113Z",
              "fluc": 4.5
            }
          ],
          "open": {
            "timestamp": "2025-12-10T22:03:39.103391876Z",
            "fluc": 7.5
          },
          "high": {
            "timestamp": "2025-12-10T22:03:39.103391876Z",
            "fluc": 7.5
          },
          "low": {
            "timestamp": "2025-12-10T22:54:47.904991308Z",
            "fluc": 4.5
          },
          "nine_am": {
            "timestamp": "0001-01-01T00:00:00Z",
            "fluc": 0
          }
        }
      },
      {
        "entrant_id": "5d494adf-4d02-4077-a2b8-a05e5c9ac160",
        "market_name": "Final Field",
        "primary_market": true,
        "name": "My Snap",
        "is_scratched": false,
        "gear": "",
        "best_time": "19.67",
        "odds": {
          "fixed_win": 21,
          "fixed_place": 2.7
        },
        "scratch_time": 0,
        "barrier": 8,
        "runner_number": 8,
        "prize_money": "2880",
        "age": 2,
        "sex": "D",
        "colour": "BDL",
        "silk_colours": "",
        "silk_url_64x64": "",
        "silk_url_128x128": "",
        "form_comment": null,
        "class_level": "",
        "jockey": "",
        "apprentice_indicator": "",
        "allowance_weight": "",
        "owners": "Tribe Synd S Tribe,K Tribe",
        "country": "AUS",
        "trainer_name": "Karen Tribe",
        "last_twenty_starts": "2573563755",
        "sire": "JETT BLACK BOB (AUS)",
        "dam": "MY GLORIOUS GAL (AUS)",
        "breeding": "d JETT BLACK BOB (AUS)-MY GLORIOUS GAL (AUS)",
        "weight": {
          "allocated": "",
          "total": ""
        },
        "favourite": false,
        "mover": false,
        "speedmap": {
          "settling_lengths": 4,
          "entrant_id": "5d494adf-4d02-4077-a2b8-a05e5c9ac160",
          "label": "Midfield"
        },
        "form_indicators": null,
        "past_performances": null,
        "jockey_past_performances": null,
        "trainer_location": "CHURCHABLE",
        "meta": null,
        "flucs": [
          27,
          26,
          23,
          21,
          20,
          21
        ],
        "scr_time": null,
        "competitor_id": "",
        "ride_guide_exists": false,
        "ride_guide_thumbnail": "",
        "ride_guide_file": "",
        "flucs_with_timestamp": {
          "last_six": [
            {
              "timestamp": "2025-12-10T22:36:50.602750629Z",
              "fluc": 27
            },
            {
              "timestamp": "2025-12-10T22:38:13.904124539Z",
              "fluc": 26
            },
            {
              "timestamp": "2025-12-10T22:49:07.004043347Z",
              "fluc": 23
            },
            {
              "timestamp": "2025-12-10T23:01:36.006550659Z",
              "fluc": 21
            },
            {
              "timestamp": "2025-12-10T23:02:05.410753866Z",
              "fluc": 20
            },
            {
              "timestamp": "2025-12-10T23:04:17.003149823Z",
              "fluc": 21
            }
          ],
          "open": {
            "timestamp": "2025-12-10T22:03:39.103453708Z",
            "fluc": 26
          },
          "high": {
            "timestamp": "2025-12-10T22:33:36.714500598Z",
            "fluc": 34
          },
          "low": {
            "timestamp": "2025-12-10T23:02:05.410753866Z",
            "fluc": 20
          },
          "nine_am": {
            "timestamp": "0001-01-01T00:00:00Z",
            "fluc": 0
          }
        }
      }
    ],
    "derivatives": null,
    "mover": {
      "entrant_id": "dbe1f8ed-7326-40e1-88cc-f46bb2b122c8",
      "market_name": "Final Field",
      "primary_market": true,
      "name": "Dad's Vision",
      "is_scratched": false,
      "gear": "",
      "best_time": "19.50",
      "odds": {
        "fixed_win": 4.5,
        "fixed_place": 1.45
      },
      "scratch_time": 0,
      "barrier": 7,
      "runner_number": 7,
      "prize_money": "3260",
      "age": 3,
      "sex": "D",
      "colour": "BL",
      "silk_colours": "",
      "silk_url_64x64": "",
      "silk_url_128x128": "",
      "form_comment": null,
      "class_level": "",
      "jockey": "",
      "apprentice_indicator": "",
      "allowance_weight": "",
      "owners": "Peter Young",
      "country": "AUS",
      "trainer_name": "Peter Young",
      "last_twenty_starts": "178x37",
      "sire": "MEPUNGA BLAZER (AUS)",
      "dam": "SUTTON'S LASS (AUS)",
      "breeding": "d MEPUNGA BLAZER (AUS)-SUTTON'S LASS (AUS)",
      "weight": {
        "allocated": "",
        "total": ""
      },
      "favourite": false,
      "mover": true,
      "speedmap": {
        "settling_lengths": 8,
        "entrant_id": "dbe1f8ed-7326-40e1-88cc-f46bb2b122c8"
      },
      "form_indicators": null,
      "past_performances": null,
      "jockey_past_performances": null,
      "trainer_location": "Prenzlau"
    },
    "big_bets": null,
    "live_bets": null,
    "biggest_bet": null,
    "money_tracker": null,
    "error": ""
  }
}