{
  "header": {
    "title": "Event Details: d5771732-1588-4890-9045-9b62c5816727",
    "generated_time": "2026-05-09T00:19:32.600836389Z",
    "url": "/affiliates/v1/racing/events/d5771732-1588-4890-9045-9b62c5816727?enc=json&include_form=true&include_odds=true&include_flucs=true&include_speedmap=true&include_past_performances=true&include_form_indicators=true&include_jockey_stats=true&include_trainer_stats=true"
  },
  "params": {
    "enc": "json",
    "id": "d5771732-1588-4890-9045-9b62c5816727",
    "present_overlay": false,
    "with_big_bets": false,
    "with_live_bets": false,
    "with_money_tracker": false,
    "with_biggest_bet": false,
    "will_pays": false,
    "with_tote_trends_data": false,
    "bet_type_filter": "",
    "bets_limit": 10
  },
  "data": {
    "race": {
      "event_id": "d5771732-1588-4890-9045-9b62c5816727",
      "meeting_name": "Albion Park",
      "display_meeting_name": "Albion Park",
      "meeting_id": "aa93e240-d234-5c04-90bb-c6176c87aaf6",
      "status": "Open",
      "description": "Nutrien Equine Band 5 Pace",
      "advertised_start": 1778314500,
      "actual_start": 1778314500,
      "advertised_start_string": "2026-05-09 08:15:00 +0000 UTC",
      "actual_start_string": "2026-05-09 08:15:00 +0000 UTC",
      "race_number": 3,
      "type": "H",
      "start_type": "Mobile",
      "country": "AUS",
      "state": "QLD",
      "distance": 2138,
      "weather": "FINE",
      "form_guide": "",
      "comment": "APPLIED NZ (1) has had little luck from wide barriers of late but has still managed some good efforts including a close second here three back. He'll relish the ace draw having led to win the last time he started from there. DOUGS FLAME (2) has been solid without a lot of luck since switching form NSW, working last time and coming from the back row prior. Draws well and owns a good record at this distance. Expect him to be prominent. SIR RICHARD LEE (8) enjoyed a class drop for an easy last-start win by more than 11 metres at Redcliffe. Draws for a trail and his record at this circuit and distance is encouraging. COMMODORE JUJON (5) deserves respect having come from the back row to win his last two outings.",
      "silk_base_url": "drr38safykj6s.cloudfront.net",
      "track_condition": "Good",
      "track_direction": "Right",
      "silk_url": "https://cdn.prod.pricekinetics.com/silks/sprites/cerberus/betmakers-cmFjZToxOTk3MDM2_SPRITE_64x64.png",
      "entrant_count": 12,
      "positions_paid": 3,
      "video_channels": [
        "Live1"
      ],
      "video_channels_meta": {
        "Live1": {
          "RaceNo": 3,
          "RaceType": "H",
          "SlotType": "",
          "SlotTitle": "",
          "VenueName": "Albion Park",
          "CrossPoint": 22,
          "RacePriority": "1",
          "SlotDuration": "",
          "SchedulerNote": "P1 (Metropolitan) Prize Money: $14,980",
          "CrossPointName": "SKY 03",
          "SlotDescription": "",
          "UtcRaceStartTime": "2026-05-09T08:15:00Z",
          "VenueCountryCode": "AU",
          "VenueProviderName": "SKY",
          "DisplayRaceStartTime": "2026-05-09T18:15:00",
          "SchedulerNotePriority": "None"
        }
      },
      "tips": [
        "523da2be-3ba6-45bf-97c3-fcfdba9f1819",
        "3b255656-ccfe-4982-8804-65c38ec16962",
        "7bc54fcd-07dd-45f8-b939-349045d06972",
        "5ce84a3f-74da-4ac8-92c8-bd9d6ca76bd5"
      ],
      "rail_position": "",
      "group": "",
      "prize_monies": {
        "10th": 240,
        "1st": 8379,
        "2nd": 2394,
        "3rd": 1197,
        "4th": 798,
        "5th": 532,
        "6th": 240,
        "7th": 240,
        "8th": 240,
        "9th": 240,
        "total_value": 14980
      },
      "track_home_straight": 0
    },
    "favourite": {
      "entrant_id": "523da2be-3ba6-45bf-97c3-fcfdba9f1819",
      "market_name": "Final Field",
      "primary_market": true,
      "name": "Applied Nz",
      "is_scratched": false,
      "gear": "[Blinkers - Murphy Blind N/S ON]",
      "odds": {
        "fixed_win": 1.35,
        "fixed_place": 1.04
      },
      "scratch_time": 0,
      "barrier": 1,
      "barrier_position": "Fr1",
      "runner_number": 1,
      "prize_money": "118636",
      "age": 5,
      "sex": "G",
      "colour": "B",
      "silk_colours": "GREEN, BLACK S & HOOPED SLEEVES",
      "silk_url_64x64": "https://cdn.prod.pricekinetics.com/silks/events/racing/betmakers-cmFjZToxOTk3MDM2/applied-nz_64x64.png",
      "silk_url_128x128": "https://cdn.prod.pricekinetics.com/silks/events/racing/betmakers-cmFjZToxOTk3MDM2/applied-nz_128x128.png",
      "form_comment": null,
      "class_level": "",
      "jockey": "Nathan Dawson",
      "apprentice_indicator": "",
      "allowance_weight": "",
      "owners": "N R Elder",
      "country": "NZ",
      "trainer_name": "Donny Smith",
      "last_twenty_starts": "3222414279",
      "sire": "SWEET LOU (USA)",
      "dam": "PEARL WHITE (NZ)",
      "breeding": "5 g SWEET LOU (USA)-PEARL WHITE (NZ)",
      "weight": {
        "allocated": "",
        "total": ""
      },
      "favourite": false,
      "mover": false,
      "speedmap": {
        "settling_lengths": 9,
        "entrant_id": "523da2be-3ba6-45bf-97c3-fcfdba9f1819"
      },
      "form_indicators": [
        {
          "name": "Driver In Form",
          "group": "Driver",
          "negative": false,
          "priority": 190
        },
        {
          "name": "Driver Flying",
          "group": "Driver",
          "negative": false,
          "priority": 160
        }
      ],
      "past_performances": null,
      "jockey_past_performances": null,
      "trainer_location": "Redcliffe"
    },
    "runners": [
      {
        "entrant_id": "523da2be-3ba6-45bf-97c3-fcfdba9f1819",
        "market_name": "Final Field",
        "primary_market": true,
        "name": "Applied Nz",
        "is_scratched": false,
        "gear": "[Blinkers - Murphy Blind N/S ON]",
        "odds": {
          "fixed_win": 1.35,
          "fixed_place": 1.04
        },
        "scratch_time": 0,
        "barrier": 1,
        "barrier_position": "Fr1",
        "runner_number": 1,
        "prize_money": "118636",
        "age": 5,
        "sex": "G",
        "colour": "B",
        "silk_colours": "GREEN, BLACK S & HOOPED SLEEVES",
        "silk_url_64x64": "https://cdn.prod.pricekinetics.com/silks/events/racing/betmakers-cmFjZToxOTk3MDM2/applied-nz_64x64.png",
        "silk_url_128x128": "https://cdn.prod.pricekinetics.com/silks/events/racing/betmakers-cmFjZToxOTk3MDM2/applied-nz_128x128.png",
        "form_comment": null,
        "class_level": "",
        "jockey": "Nathan Dawson",
        "apprentice_indicator": "",
        "allowance_weight": "",
        "owners": "N R Elder",
        "country": "NZ",
        "trainer_name": "Donny Smith",
        "last_twenty_starts": "3222414279",
        "sire": "SWEET LOU (USA)",
        "dam": "PEARL WHITE (NZ)",
        "breeding": "5 g SWEET LOU (USA)-PEARL WHITE (NZ)",
        "weight": {
          "allocated": "",
          "total": ""
        },
        "favourite": true,
        "mover": true,
        "speedmap": {
          "settling_lengths": 9,
          "entrant_id": "523da2be-3ba6-45bf-97c3-fcfdba9f1819",
          "label": "Leader"
        },
        "form_indicators": [
          {
            "name": "Driver In Form",
            "group": "Driver",
            "negative": false,
            "priority": 190
          },
          {
            "name": "Driver Flying",
            "group": "Driver",
            "negative": false,
            "priority": 160
          }
        ],
        "past_performances": null,
        "jockey_past_performances": null,
        "trainer_location": "Redcliffe",
        "meta": null,
        "flucs": [
          1.7,
          1.35
        ],
        "scr_time": null,
        "competitor_id": "",
        "ride_guide_exists": false,
        "ride_guide_thumbnail": "",
        "ride_guide_file": "",
        "flucs_with_timestamp": {
          "last_six": [
            {
              "timestamp": "2026-05-09T00:04:58.085189118Z",
              "fluc": 1.7
            },
            {
              "timestamp": "2026-05-09T00:07:09.608686985Z",
              "fluc": 1.35
            }
          ],
          "open": {
            "timestamp": "2026-05-09T00:04:58.085189118Z",
            "fluc": 1.7
          },
          "high": {
            "timestamp": "2026-05-09T00:04:58.085189118Z",
            "fluc": 1.7
          },
          "low": {
            "timestamp": "2026-05-09T00:07:09.608686985Z",
            "fluc": 1.35
          },
          "nine_am": {
            "timestamp": "0001-01-01T00:00:00Z",
            "fluc": 0
          }
        }
      },
      {
        "entrant_id": "3b255656-ccfe-4982-8804-65c38ec16962",
        "market_name": "Final Field",
        "primary_market": true,
        "name": "Dougs Flame",
        "is_scratched": false,
        "gear": "[Bit - Snaffle ON, Blinkers - Hood ON, Bit - Pulling OFF, Lugging Pole N/S OFF, Blinkers - Sliding Dolly Vardens OFF]",
        "odds": {
          "fixed_win": 5,
          "fixed_place": 1.4
        },
        "scratch_time": 0,
        "barrier": 2,
        "barrier_position": "Fr2",
        "runner_number": 2,
        "prize_money": "117246",
        "age": 5,
        "sex": "H",
        "colour": "B",
        "silk_colours": "DARK BLUE, RED DIAMONDS, HOOPED SLEEVES",
        "silk_url_64x64": "https://cdn.prod.pricekinetics.com/silks/events/racing/betmakers-cmFjZToxOTk3MDM2/dougs-flame_64x64.png",
        "silk_url_128x128": "https://cdn.prod.pricekinetics.com/silks/events/racing/betmakers-cmFjZToxOTk3MDM2/dougs-flame_128x128.png",
        "form_comment": null,
        "class_level": "",
        "jockey": "Leonard Cain",
        "apprentice_indicator": "",
        "allowance_weight": "",
        "owners": "H M Plumb, C Durden",
        "country": "AUS",
        "trainer_name": "Jack Butler",
        "last_twenty_starts": "2254098757",
        "sire": "FLAMING FLUTTER (NZ)",
        "dam": "DOUGS COURAGE (USA)",
        "breeding": "5 h FLAMING FLUTTER (NZ)-DOUGS COURAGE (USA)",
        "weight": {
          "allocated": "",
          "total": ""
        },
        "favourite": false,
        "mover": false,
        "speedmap": {
          "settling_lengths": 8,
          "entrant_id": "3b255656-ccfe-4982-8804-65c38ec16962",
          "label": "Leader"
        },
        "form_indicators": null,
        "past_performances": null,
        "jockey_past_performances": null,
        "trainer_location": "Logan Village",
        "meta": null,
        "flucs": [
          4.8,
          5
        ],
        "scr_time": null,
        "competitor_id": "",
        "ride_guide_exists": false,
        "ride_guide_thumbnail": "",
        "ride_guide_file": "",
        "flucs_with_timestamp": {
          "last_six": [
            {
              "timestamp": "2026-05-09T00:04:58.085205982Z",
              "fluc": 4.8
            },
            {
              "timestamp": "2026-05-09T00:07:50.28261649Z",
              "fluc": 5
            }
          ],
          "open": {
            "timestamp": "2026-05-09T00:04:58.085205982Z",
            "fluc": 4.8
          },
          "high": {
            "timestamp": "2026-05-09T00:07:50.28261649Z",
            "fluc": 5
          },
          "low": {
            "timestamp": "2026-05-09T00:04:58.085205982Z",
            "fluc": 4.8
          },
          "nine_am": {
            "timestamp": "0001-01-01T00:00:00Z",
            "fluc": 0
          }
        }
      },
      {
        "entrant_id": "79afa760-5577-4ea2-87c6-dd28aede17f8",
        "market_name": "Final Field",
        "primary_market": true,
        "name": "Rocknroll Walla",
        "is_scratched": true,
        "gear": "",
        "odds": {
          "fixed_win": 0,
          "fixed_place": 0
        },
        "scratch_time": 1778194567,
        "barrier": 3,
        "barrier_position": "Fr-",
        "runner_number": 3,
        "prize_money": "98015",
        "age": 7,
        "sex": "G",
        "colour": "BL",
        "silk_colours": "BLACK, FIVE YELLOW SPOTS, BLACK SLEEVES, TWO YELLOW ARMBANDS",
        "silk_url_64x64": "https://cdn.prod.pricekinetics.com/silks/events/racing/betmakers-cmFjZToxOTk3MDM2/rocknroll-walla_64x64.png",
        "silk_url_128x128": "https://cdn.prod.pricekinetics.com/silks/events/racing/betmakers-cmFjZToxOTk3MDM2/rocknroll-walla_128x128.png",
        "form_comment": null,
        "class_level": "",
        "jockey": "Jordan Topping",
        "apprentice_indicator": "",
        "allowance_weight": "",
        "owners": "D P Barnes, B Barnes, A D Barnes, Z Barnes",
        "country": "AUS",
        "trainer_name": "C P Martin",
        "last_twenty_starts": "3600x8x455",
        "sire": "ROCK N ROLL HEAVEN (USA)",
        "dam": "INDI ROSE (NZ)",
        "breeding": "7 g ROCK N ROLL HEAVEN (USA)-INDI ROSE (NZ)",
        "weight": {
          "allocated": "",
          "total": ""
        },
        "favourite": false,
        "mover": false,
        "speedmap": {
          "settling_lengths": 1,
          "entrant_id": "79afa760-5577-4ea2-87c6-dd28aede17f8",
          "label": "invalid settling lengths"
        },
        "form_indicators": null,
        "past_performances": null,
        "jockey_past_performances": null,
        "trainer_location": "Peak Crossing",
        "meta": null,
        "flucs": [],
        "scr_time": "2026-05-07T22:56:07Z",
        "competitor_id": "",
        "ride_guide_exists": false,
        "ride_guide_thumbnail": "",
        "ride_guide_file": "",
        "flucs_with_timestamp": {
          "last_six": [],
          "open": {
            "timestamp": "0001-01-01T00:00:00Z",
            "fluc": 0
          },
          "high": {
            "timestamp": "0001-01-01T00:00:00Z",
            "fluc": 0
          },
          "low": {
            "timestamp": "0001-01-01T00:00:00Z",
            "fluc": 0
          },
          "nine_am": {
            "timestamp": "0001-01-01T00:00:00Z",
            "fluc": 0
          }
        }
      },
      {
        "entrant_id": "62fc8b53-40e1-4fb6-9f48-b828e0c146e4",
        "market_name": "Final Field",
        "primary_market": true,
        "name": "Jekamias Nz",
        "is_scratched": false,
        "gear": "",
        "odds": {
          "fixed_win": 61,
          "fixed_place": 7
        },
        "scratch_time": 0,
        "barrier": 3,
        "barrier_position": "Fr3",
        "runner_number": 4,
        "prize_money": "102891",
        "age": 7,
        "sex": "G",
        "colour": "B",
        "silk_colours": "GREEN, YELLOW SLEEVES",
        "silk_url_64x64": "https://cdn.prod.pricekinetics.com/silks/events/racing/betmakers-cmFjZToxOTk3MDM2/jekamias-nz_64x64.png",
        "silk_url_128x128": "https://cdn.prod.pricekinetics.com/silks/events/racing/betmakers-cmFjZToxOTk3MDM2/jekamias-nz_128x128.png",
        "form_comment": null,
        "class_level": "",
        "jockey": "Lola Weidemann",
        "apprentice_indicator": "",
        "allowance_weight": "",
        "owners": "J W Powderly, C R Powderly",
        "country": "NZ",
        "trainer_name": "Lola Weidemann",
        "last_twenty_starts": "1361825165",
        "sire": "BETTERTHANCHEDDAR (USA)",
        "dam": "DESLUNA (NZ)",
        "breeding": "7 g BETTERTHANCHEDDAR (USA)-DESLUNA (NZ)",
        "weight": {
          "allocated": "",
          "total": ""
        },
        "favourite": false,
        "mover": false,
        "speedmap": {
          "settling_lengths": 7,
          "entrant_id": "62fc8b53-40e1-4fb6-9f48-b828e0c146e4",
          "label": "Pace"
        },
        "form_indicators": null,
        "past_performances": null,
        "jockey_past_performances": null,
        "trainer_location": "Clifton",
        "meta": null,
        "flucs": [
          41,
          46,
          61
        ],
        "scr_time": null,
        "competitor_id": "",
        "ride_guide_exists": false,
        "ride_guide_thumbnail": "",
        "ride_guide_file": "",
        "flucs_with_timestamp": {
          "last_six": [
            {
              "timestamp": "2026-05-09T00:04:58.085336322Z",
              "fluc": 41
            },
            {
              "timestamp": "2026-05-09T00:07:50.282430395Z",
              "fluc": 46
            },
            {
              "timestamp": "2026-05-09T00:07:58.628495656Z",
              "fluc": 61
            }
          ],
          "open": {
            "timestamp": "2026-05-09T00:04:58.085336322Z",
            "fluc": 41
          },
          "high": {
            "timestamp": "2026-05-09T00:07:58.628495656Z",
            "fluc": 61
          },
          "low": {
            "timestamp": "2026-05-09T00:04:58.085336322Z",
            "fluc": 41
          },
          "nine_am": {
            "timestamp": "0001-01-01T00:00:00Z",
            "fluc": 0
          }
        }
      },
      {
        "entrant_id": "5ce84a3f-74da-4ac8-92c8-bd9d6ca76bd5",
        "market_name": "Final Field",
        "primary_market": true,
        "name": "Commodore Jujon",
        "is_scratched": false,
        "gear": "",
        "odds": {
          "fixed_win": 11,
          "fixed_place": 2.35
        },
        "scratch_time": 0,
        "barrier": 4,
        "barrier_position": "Fr4",
        "runner_number": 5,
        "prize_money": "298481",
        "age": 10,
        "sex": "G",
        "colour": "B",
        "silk_colours": "RED, BLUE V & STRIPED SLEEVES",
        "silk_url_64x64": "https://cdn.prod.pricekinetics.com/silks/events/racing/betmakers-cmFjZToxOTk3MDM2/commodore-jujon_64x64.png",
        "silk_url_128x128": "https://cdn.prod.pricekinetics.com/silks/events/racing/betmakers-cmFjZToxOTk3MDM2/commodore-jujon_128x128.png",
        "form_comment": null,
        "class_level": "",
        "jockey": "Grant Dixon",
        "apprentice_indicator": "",
        "allowance_weight": "",
        "owners": "J Mammino",
        "country": "AUS",
        "trainer_name": "Grant Dixon",
        "last_twenty_starts": "6265352911",
        "sire": "SOUTH PARK HANOVER (USA)",
        "dam": "FREE (USA)",
        "breeding": "10 g SOUTH PARK HANOVER (USA)-FREE (USA)",
        "weight": {
          "allocated": "",
          "total": ""
        },
        "favourite": false,
        "mover": false,
        "speedmap": {
          "settling_lengths": 8,
          "entrant_id": "5ce84a3f-74da-4ac8-92c8-bd9d6ca76bd5",
          "label": "Leader"
        },
        "form_indicators": [
          {
            "name": "Going for the Hat-Trick ",
            "group": "Win",
            "negative": false,
            "priority": 230
          }
        ],
        "past_performances": null,
        "jockey_past_performances": null,
        "trainer_location": "Tamborine",
        "meta": null,
        "flucs": [
          10,
          11
        ],
        "scr_time": null,
        "competitor_id": "",
        "ride_guide_exists": false,
        "ride_guide_thumbnail": "",
        "ride_guide_file": "",
        "flucs_with_timestamp": {
          "last_six": [
            {
              "timestamp": "2026-05-09T00:04:58.085217871Z",
              "fluc": 10
            },
            {
              "timestamp": "2026-05-09T00:07:50.282364909Z",
              "fluc": 11
            }
          ],
          "open": {
            "timestamp": "2026-05-09T00:04:58.085217871Z",
            "fluc": 10
          },
          "high": {
            "timestamp": "2026-05-09T00:07:50.282364909Z",
            "fluc": 11
          },
          "low": {
            "timestamp": "2026-05-09T00:04:58.085217871Z",
            "fluc": 10
          },
          "nine_am": {
            "timestamp": "0001-01-01T00:00:00Z",
            "fluc": 0
          }
        }
      },
      {
        "entrant_id": "9e0989a0-7b1c-4439-b82d-f5d7c0f6efde",
        "market_name": "Final Field",
        "primary_market": true,
        "name": "Mister Reactor",
        "is_scratched": false,
        "gear": "",
        "odds": {
          "fixed_win": 71,
          "fixed_place": 8
        },
        "scratch_time": 0,
        "barrier": 5,
        "barrier_position": "Fr5",
        "runner_number": 6,
        "prize_money": "154923",
        "age": 7,
        "sex": "H",
        "colour": "B",
        "silk_colours": "BLUE, WHITE SLEEVES, BLUE DIAMOND STRIPE",
        "silk_url_64x64": "https://cdn.prod.pricekinetics.com/silks/events/racing/betmakers-cmFjZToxOTk3MDM2/mister-reactor_64x64.png",
        "silk_url_128x128": "https://cdn.prod.pricekinetics.com/silks/events/racing/betmakers-cmFjZToxOTk3MDM2/mister-reactor_128x128.png",
        "form_comment": null,
        "class_level": "",
        "jockey": "Shane Graham",
        "apprentice_indicator": "",
        "allowance_weight": "",
        "owners": "D Hellyer",
        "country": "AUS",
        "trainer_name": "Geoff Dawson",
        "last_twenty_starts": "4127253440",
        "sire": "AUCKLAND REACTOR (NZ)",
        "dam": "SHECHOSEUS (AUS)",
        "breeding": "7 h AUCKLAND REACTOR (NZ)-SHECHOSEUS (AUS)",
        "weight": {
          "allocated": "",
          "total": ""
        },
        "favourite": false,
        "mover": false,
        "speedmap": {
          "settling_lengths": 4,
          "entrant_id": "9e0989a0-7b1c-4439-b82d-f5d7c0f6efde",
          "label": "Midfield"
        },
        "form_indicators": null,
        "past_performances": null,
        "jockey_past_performances": null,
        "trainer_location": "Wanora",
        "meta": null,
        "flucs": [
          51,
          67,
          71
        ],
        "scr_time": null,
        "competitor_id": "",
        "ride_guide_exists": false,
        "ride_guide_thumbnail": "",
        "ride_guide_file": "",
        "flucs_with_timestamp": {
          "last_six": [
            {
              "timestamp": "2026-05-09T00:04:58.085370894Z",
              "fluc": 51
            },
            {
              "timestamp": "2026-05-09T00:07:58.628595781Z",
              "fluc": 67
            },
            {
              "timestamp": "2026-05-09T00:16:22.63127606Z",
              "fluc": 71
            }
          ],
          "open": {
            "timestamp": "2026-05-09T00:04:58.085370894Z",
            "fluc": 51
          },
          "high": {
            "timestamp": "2026-05-09T00:16:22.63127606Z",
            "fluc": 71
          },
          "low": {
            "timestamp": "2026-05-09T00:04:58.085370894Z",
            "fluc": 51
          },
          "nine_am": {
            "timestamp": "0001-01-01T00:00:00Z",
            "fluc": 0
          }
        }
      },
      {
        "entrant_id": "5f3cfe36-37f5-456b-a23f-3128956f2044",
        "market_name": "Final Field",
        "primary_market": true,
        "name": "My Ultimate Flynn Nz",
        "is_scratched": false,
        "gear": "[Blinkers - Block OFF]",
        "odds": {
          "fixed_win": 16,
          "fixed_place": 3.1
        },
        "scratch_time": 0,
        "barrier": 6,
        "barrier_position": "Fr6",
        "runner_number": 7,
        "prize_money": "91100",
        "age": 5,
        "sex": "H",
        "colour": "B",
        "silk_colours": "BLACK, YELLOW YOKE, BRACES & BAND, BLACK HORSESHOES, YELLOW SLEEVES",
        "silk_url_64x64": "https://cdn.prod.pricekinetics.com/silks/events/racing/betmakers-cmFjZToxOTk3MDM2/my-ultimate-flynn-nz_64x64.png",
        "silk_url_128x128": "https://cdn.prod.pricekinetics.com/silks/events/racing/betmakers-cmFjZToxOTk3MDM2/my-ultimate-flynn-nz_128x128.png",
        "form_comment": null,
        "class_level": "",
        "jockey": "Matt Elkins",
        "apprentice_indicator": "",
        "allowance_weight": "",
        "owners": "M K Jarrett, C Jarrett, S J Smith",
        "country": "NZ",
        "trainer_name": "Matt Elkins",
        "last_twenty_starts": "17434240x2",
        "sire": "BETTORS DELIGHT (USA)",
        "dam": "LA BASTILLE (NZ)",
        "breeding": "5 h BETTORS DELIGHT (USA)-LA BASTILLE (NZ)",
        "weight": {
          "allocated": "",
          "total": ""
        },
        "favourite": false,
        "mover": false,
        "speedmap": {
          "settling_lengths": 8,
          "entrant_id": "5f3cfe36-37f5-456b-a23f-3128956f2044",
          "label": "Leader"
        },
        "form_indicators": null,
        "past_performances": null,
        "jockey_past_performances": null,
        "trainer_location": "Coominya",
        "meta": null,
        "flucs": [
          13,
          14,
          15,
          16
        ],
        "scr_time": null,
        "competitor_id": "",
        "ride_guide_exists": false,
        "ride_guide_thumbnail": "",
        "ride_guide_file": "",
        "flucs_with_timestamp": {
          "last_six": [
            {
              "timestamp": "2026-05-09T00:04:58.085179997Z",
              "fluc": 13
            },
            {
              "timestamp": "2026-05-09T00:07:50.282574781Z",
              "fluc": 14
            },
            {
              "timestamp": "2026-05-09T00:11:05.627564628Z",
              "fluc": 15
            },
            {
              "timestamp": "2026-05-09T00:17:19.399621395Z",
              "fluc": 16
            }
          ],
          "open": {
            "timestamp": "2026-05-09T00:04:58.085179997Z",
            "fluc": 13
          },
          "high": {
            "timestamp": "2026-05-09T00:17:19.399621395Z",
            "fluc": 16
          },
          "low": {
            "timestamp": "2026-05-09T00:04:58.085179997Z",
            "fluc": 13
          },
          "nine_am": {
            "timestamp": "0001-01-01T00:00:00Z",
            "fluc": 0
          }
        }
      },
      {
        "entrant_id": "7bc54fcd-07dd-45f8-b939-349045d06972",
        "market_name": "Final Field",
        "primary_market": true,
        "name": "Sir Richard Lee",
        "is_scratched": false,
        "gear": "",
        "odds": {
          "fixed_win": 5.5,
          "fixed_place": 1.55
        },
        "scratch_time": 0,
        "barrier": 1,
        "barrier_position": "Sr1",
        "runner_number": 8,
        "prize_money": "225691",
        "age": 8,
        "sex": "G",
        "colour": "BR",
        "silk_colours": "YELLOW, BLACK YOKE & BRACES, YELLOW STARS, BLACK SLEEVES, YELLOW CUFFS, \"TC\" INITIALS",
        "silk_url_64x64": "https://cdn.prod.pricekinetics.com/silks/events/racing/betmakers-cmFjZToxOTk3MDM2/sir-richard-lee_64x64.png",
        "silk_url_128x128": "https://cdn.prod.pricekinetics.com/silks/events/racing/betmakers-cmFjZToxOTk3MDM2/sir-richard-lee_128x128.png",
        "form_comment": null,
        "class_level": "",
        "jockey": "Tom Callaghan",
        "apprentice_indicator": "",
        "allowance_weight": "",
        "owners": "K A Lee, V J Muscat, C J J Muscat",
        "country": "AUS",
        "trainer_name": "T M Callaghan",
        "last_twenty_starts": "2143180981",
        "sire": "HESTON BLUE CHIP (USA)",
        "dam": "MAJEUR LE CREST (AUS)",
        "breeding": "8 g HESTON BLUE CHIP (USA)-MAJEUR LE CREST (AUS)",
        "weight": {
          "allocated": "",
          "total": ""
        },
        "favourite": false,
        "mover": false,
        "speedmap": {
          "settling_lengths": 9,
          "entrant_id": "7bc54fcd-07dd-45f8-b939-349045d06972",
          "label": "Leader"
        },
        "form_indicators": [
          {
            "name": "Dominant Win Last Start",
            "group": "Last_Start_Winner",
            "negative": false,
            "priority": 200
          }
        ],
        "past_performances": null,
        "jockey_past_performances": null,
        "trainer_location": "Patrick Estate",
        "meta": null,
        "flucs": [
          5.5
        ],
        "scr_time": null,
        "competitor_id": "",
        "ride_guide_exists": false,
        "ride_guide_thumbnail": "",
        "ride_guide_file": "",
        "flucs_with_timestamp": {
          "last_six": [
            {
              "timestamp": "2026-05-09T00:04:58.085160543Z",
              "fluc": 5.5
            }
          ],
          "open": {
            "timestamp": "2026-05-09T00:04:58.085160543Z",
            "fluc": 5.5
          },
          "high": {
            "timestamp": "2026-05-09T00:04:58.085160543Z",
            "fluc": 5.5
          },
          "low": {
            "timestamp": "2026-05-09T00:04:58.085160543Z",
            "fluc": 5.5
          },
          "nine_am": {
            "timestamp": "0001-01-01T00:00:00Z",
            "fluc": 0
          }
        }
      },
      {
        "entrant_id": "8f5c3f32-5bf4-4463-bc72-fbdf2e058f4f",
        "market_name": "Final Field",
        "primary_market": true,
        "name": "Credulous",
        "is_scratched": false,
        "gear": "",
        "odds": {
          "fixed_win": 23,
          "fixed_place": 3.3
        },
        "scratch_time": 0,
        "barrier": 2,
        "barrier_position": "Sr2",
        "runner_number": 9,
        "prize_money": "137948",
        "age": 6,
        "sex": "M",
        "colour": "BR/BL",
        "silk_colours": "WHITE, RED BRACES, BAND & YOKE WITH WHITE STARS, RED SLEEVES, WHITE STARS",
        "silk_url_64x64": "https://cdn.prod.pricekinetics.com/silks/events/racing/betmakers-cmFjZToxOTk3MDM2/credulous_64x64.png",
        "silk_url_128x128": "https://cdn.prod.pricekinetics.com/silks/events/racing/betmakers-cmFjZToxOTk3MDM2/credulous_128x128.png",
        "form_comment": null,
        "class_level": "",
        "jockey": "Narissa Elkins",
        "apprentice_indicator": "",
        "allowance_weight": "",
        "owners": "N R Dewhurst, K F Purdon",
        "country": "AUS",
        "trainer_name": "Matt Elkins",
        "last_twenty_starts": "3435165726",
        "sire": "BETTING LINE (USA)",
        "dam": "ART CASTLE (AUS)",
        "breeding": "6 m BETTING LINE (USA)-ART CASTLE (AUS)",
        "weight": {
          "allocated": "",
          "total": ""
        },
        "favourite": false,
        "mover": false,
        "speedmap": {
          "settling_lengths": 6,
          "entrant_id": "8f5c3f32-5bf4-4463-bc72-fbdf2e058f4f",
          "label": "Off Pace"
        },
        "form_indicators": null,
        "past_performances": null,
        "jockey_past_performances": null,
        "trainer_location": "Coominya",
        "meta": null,
        "flucs": [
          21,
          23
        ],
        "scr_time": null,
        "competitor_id": "",
        "ride_guide_exists": false,
        "ride_guide_thumbnail": "",
        "ride_guide_file": "",
        "flucs_with_timestamp": {
          "last_six": [
            {
              "timestamp": "2026-05-09T00:04:58.08525031Z",
              "fluc": 21
            },
            {
              "timestamp": "2026-05-09T00:07:58.628449316Z",
              "fluc": 23
            }
          ],
          "open": {
            "timestamp": "2026-05-09T00:04:58.08525031Z",
            "fluc": 21
          },
          "high": {
            "timestamp": "2026-05-09T00:07:58.628449316Z",
            "fluc": 23
          },
          "low": {
            "timestamp": "2026-05-09T00:04:58.08525031Z",
            "fluc": 21
          },
          "nine_am": {
            "timestamp": "0001-01-01T00:00:00Z",
            "fluc": 0
          }
        }
      },
      {
        "entrant_id": "91dbfa62-14e0-4750-b5b8-97300e7d7bd4",
        "market_name": "Final Field",
        "primary_market": true,
        "name": "Rocks Or Diamonds",
        "is_scratched": false,
        "gear": "",
        "odds": {
          "fixed_win": 51,
          "fixed_place": 7
        },
        "scratch_time": 0,
        "barrier": 3,
        "barrier_position": "Sr3",
        "runner_number": 10,
        "prize_money": "190796",
        "age": 9,
        "sex": "G",
        "colour": "B",
        "silk_colours": "BLACK, YELLOW SPOTS",
        "silk_url_64x64": "https://cdn.prod.pricekinetics.com/silks/events/racing/betmakers-cmFjZToxOTk3MDM2/rocks-or-diamonds_64x64.png",
        "silk_url_128x128": "https://cdn.prod.pricekinetics.com/silks/events/racing/betmakers-cmFjZToxOTk3MDM2/rocks-or-diamonds_128x128.png",
        "form_comment": null,
        "class_level": "",
        "jockey": "Adam Richardson",
        "apprentice_indicator": "",
        "allowance_weight": "",
        "owners": "R J Beaton, Estate of R McCall, Cook Boys Syndicate (Mgr: R J Cook)",
        "country": "AUS",
        "trainer_name": "Brian Mccall",
        "last_twenty_starts": "68386238x2",
        "sire": "ROCK N ROLL HEAVEN (USA)",
        "dam": "MORE DIAMONDS (AUS)",
        "breeding": "9 g ROCK N ROLL HEAVEN (USA)-MORE DIAMONDS (AUS)",
        "weight": {
          "allocated": "",
          "total": ""
        },
        "favourite": false,
        "mover": false,
        "speedmap": {
          "settling_lengths": 5,
          "entrant_id": "91dbfa62-14e0-4750-b5b8-97300e7d7bd4",
          "label": "Midfield"
        },
        "form_indicators": null,
        "past_performances": null,
        "jockey_past_performances": null,
        "trainer_location": "Churchable",
        "meta": null,
        "flucs": [
          41,
          46,
          41,
          46,
          51
        ],
        "scr_time": null,
        "competitor_id": "",
        "ride_guide_exists": false,
        "ride_guide_thumbnail": "",
        "ride_guide_file": "",
        "flucs_with_timestamp": {
          "last_six": [
            {
              "timestamp": "2026-05-09T00:04:58.085232319Z",
              "fluc": 41
            },
            {
              "timestamp": "2026-05-09T00:07:58.628504765Z",
              "fluc": 46
            },
            {
              "timestamp": "2026-05-09T00:11:05.627621682Z",
              "fluc": 41
            },
            {
              "timestamp": "2026-05-09T00:16:22.631311061Z",
              "fluc": 46
            },
            {
              "timestamp": "2026-05-09T00:17:19.399622952Z",
              "fluc": 51
            }
          ],
          "open": {
            "timestamp": "2026-05-09T00:04:58.085232319Z",
            "fluc": 41
          },
          "high": {
            "timestamp": "2026-05-09T00:17:19.399622952Z",
            "fluc": 51
          },
          "low": {
            "timestamp": "2026-05-09T00:04:58.085232319Z",
            "fluc": 41
          },
          "nine_am": {
            "timestamp": "0001-01-01T00:00:00Z",
            "fluc": 0
          }
        }
      },
      {
        "entrant_id": "da017f66-05de-49b6-95db-738cd95ec4d6",
        "market_name": "Final Field",
        "primary_market": true,
        "name": "Betterthan Popsy",
        "is_scratched": false,
        "gear": "",
        "odds": {
          "fixed_win": 51,
          "fixed_place": 7
        },
        "scratch_time": 0,
        "barrier": 4,
        "barrier_position": "Sr4",
        "runner_number": 11,
        "prize_money": "185444",
        "age": 7,
        "sex": "H",
        "colour": "B",
        "silk_colours": "BLACK & WHITE CHECKS, WHITE SLEEVES",
        "silk_url_64x64": "https://cdn.prod.pricekinetics.com/silks/events/racing/betmakers-cmFjZToxOTk3MDM2/betterthan-popsy_64x64.png",
        "silk_url_128x128": "https://cdn.prod.pricekinetics.com/silks/events/racing/betmakers-cmFjZToxOTk3MDM2/betterthan-popsy_128x128.png",
        "form_comment": null,
        "class_level": "",
        "jockey": "Jack Chapple",
        "apprentice_indicator": "",
        "allowance_weight": "",
        "owners": "P B Stanmore",
        "country": "AUS",
        "trainer_name": "Grant Dixon",
        "last_twenty_starts": "4684167846",
        "sire": "BETTERTHANCHEDDAR (USA)",
        "dam": "STEDA GEM (AUS)",
        "breeding": "7 h BETTERTHANCHEDDAR (USA)-STEDA GEM (AUS)",
        "weight": {
          "allocated": "",
          "total": ""
        },
        "favourite": false,
        "mover": false,
        "speedmap": {
          "settling_lengths": 4,
          "entrant_id": "da017f66-05de-49b6-95db-738cd95ec4d6",
          "label": "Midfield"
        },
        "form_indicators": null,
        "past_performances": null,
        "jockey_past_performances": null,
        "trainer_location": "Tamborine",
        "meta": null,
        "flucs": [
          41,
          46,
          41,
          46,
          51
        ],
        "scr_time": null,
        "competitor_id": "",
        "ride_guide_exists": false,
        "ride_guide_thumbnail": "",
        "ride_guide_file": "",
        "flucs_with_timestamp": {
          "last_six": [
            {
              "timestamp": "2026-05-09T00:04:58.085349373Z",
              "fluc": 41
            },
            {
              "timestamp": "2026-05-09T00:07:58.628452711Z",
              "fluc": 46
            },
            {
              "timestamp": "2026-05-09T00:11:05.627583241Z",
              "fluc": 41
            },
            {
              "timestamp": "2026-05-09T00:16:22.631302202Z",
              "fluc": 46
            },
            {
              "timestamp": "2026-05-09T00:17:19.399472961Z",
              "fluc": 51
            }
          ],
          "open": {
            "timestamp": "2026-05-09T00:04:58.085349373Z",
            "fluc": 41
          },
          "high": {
            "timestamp": "2026-05-09T00:17:19.399472961Z",
            "fluc": 51
          },
          "low": {
            "timestamp": "2026-05-09T00:11:05.627583241Z",
            "fluc": 41
          },
          "nine_am": {
            "timestamp": "0001-01-01T00:00:00Z",
            "fluc": 0
          }
        }
      },
      {
        "entrant_id": "f95d6c15-e134-474a-8fec-149a88738e9b",
        "market_name": "Final Field",
        "primary_market": true,
        "name": "Hot Rod Harry",
        "is_scratched": false,
        "gear": "",
        "odds": {
          "fixed_win": 41,
          "fixed_place": 6
        },
        "scratch_time": 0,
        "barrier": 5,
        "barrier_position": "Sr5",
        "runner_number": 12,
        "prize_money": "78290",
        "age": 5,
        "sex": "H",
        "colour": "B",
        "silk_colours": "ROYAL BLUE, RED DIAMONDS, BRACES & CUFFS",
        "silk_url_64x64": "https://cdn.prod.pricekinetics.com/silks/events/racing/betmakers-cmFjZToxOTk3MDM2/hot-rod-harry_64x64.png",
        "silk_url_128x128": "https://cdn.prod.pricekinetics.com/silks/events/racing/betmakers-cmFjZToxOTk3MDM2/hot-rod-harry_128x128.png",
        "form_comment": null,
        "class_level": "",
        "jockey": "Trent Dawson",
        "apprentice_indicator": "",
        "allowance_weight": "",
        "owners": "Solid Earth Pty Ltd (Mgr: K Seymour)",
        "country": "AUS",
        "trainer_name": "Trent Dawson",
        "last_twenty_starts": "2020884374",
        "sire": "AMERICAN IDEAL (USA)",
        "dam": "HAPPY FEELINGS (AUS)",
        "breeding": "5 h AMERICAN IDEAL (USA)-HAPPY FEELINGS (AUS)",
        "weight": {
          "allocated": "",
          "total": ""
        },
        "favourite": false,
        "mover": false,
        "speedmap": {
          "settling_lengths": 5,
          "entrant_id": "f95d6c15-e134-474a-8fec-149a88738e9b",
          "label": "Midfield"
        },
        "form_indicators": null,
        "past_performances": null,
        "jockey_past_performances": null,
        "trainer_location": "Clarendon",
        "meta": null,
        "flucs": [
          35,
          34,
          35,
          41,
          46,
          41
        ],
        "scr_time": null,
        "competitor_id": "",
        "ride_guide_exists": false,
        "ride_guide_thumbnail": "",
        "ride_guide_file": "",
        "flucs_with_timestamp": {
          "last_six": [
            {
              "timestamp": "2026-05-09T00:04:58.085164791Z",
              "fluc": 35
            },
            {
              "timestamp": "2026-05-09T00:05:58.329907488Z",
              "fluc": 34
            },
            {
              "timestamp": "2026-05-09T00:06:58.474651224Z",
              "fluc": 35
            },
            {
              "timestamp": "2026-05-09T00:07:50.28250832Z",
              "fluc": 41
            },
            {
              "timestamp": "2026-05-09T00:07:58.62851311Z",
              "fluc": 46
            },
            {
              "timestamp": "2026-05-09T00:11:05.627595909Z",
              "fluc": 41
            }
          ],
          "open": {
            "timestamp": "2026-05-09T00:04:58.085164791Z",
            "fluc": 35
          },
          "high": {
            "timestamp": "2026-05-09T00:07:58.62851311Z",
            "fluc": 46
          },
          "low": {
            "timestamp": "2026-05-09T00:05:58.329907488Z",
            "fluc": 34
          },
          "nine_am": {
            "timestamp": "0001-01-01T00:00:00Z",
            "fluc": 0
          }
        }
      }
    ],
    "derivatives": null,
    "mover": {
      "entrant_id": "523da2be-3ba6-45bf-97c3-fcfdba9f1819",
      "market_name": "Final Field",
      "primary_market": true,
      "name": "Applied Nz",
      "is_scratched": false,
      "gear": "[Blinkers - Murphy Blind N/S ON]",
      "odds": {
        "fixed_win": 1.35,
        "fixed_place": 1.04
      },
      "scratch_time": 0,
      "barrier": 1,
      "barrier_position": "Fr1",
      "runner_number": 1,
      "prize_money": "118636",
      "age": 5,
      "sex": "G",
      "colour": "B",
      "silk_colours": "GREEN, BLACK S & HOOPED SLEEVES",
      "silk_url_64x64": "https://cdn.prod.pricekinetics.com/silks/events/racing/betmakers-cmFjZToxOTk3MDM2/applied-nz_64x64.png",
      "silk_url_128x128": "https://cdn.prod.pricekinetics.com/silks/events/racing/betmakers-cmFjZToxOTk3MDM2/applied-nz_128x128.png",
      "form_comment": null,
      "class_level": "",
      "jockey": "Nathan Dawson",
      "apprentice_indicator": "",
      "allowance_weight": "",
      "owners": "N R Elder",
      "country": "NZ",
      "trainer_name": "Donny Smith",
      "last_twenty_starts": "3222414279",
      "sire": "SWEET LOU (USA)",
      "dam": "PEARL WHITE (NZ)",
      "breeding": "5 g SWEET LOU (USA)-PEARL WHITE (NZ)",
      "weight": {
        "allocated": "",
        "total": ""
      },
      "favourite": false,
      "mover": true,
      "speedmap": {
        "settling_lengths": 9,
        "entrant_id": "523da2be-3ba6-45bf-97c3-fcfdba9f1819"
      },
      "form_indicators": [
        {
          "name": "Driver In Form",
          "group": "Driver",
          "negative": false,
          "priority": 190
        },
        {
          "name": "Driver Flying",
          "group": "Driver",
          "negative": false,
          "priority": 160
        }
      ],
      "past_performances": null,
      "jockey_past_performances": null,
      "trainer_location": "Redcliffe"
    },
    "big_bets": null,
    "live_bets": null,
    "biggest_bet": null,
    "money_tracker": null,
    "error": ""
  }
}