{
  "header": {
    "title": "Event Details: 57c7104e-3b64-412e-85ef-d637f92ea25f",
    "generated_time": "2026-05-02T00:13:50.045811223Z",
    "url": "/affiliates/v1/racing/events/57c7104e-3b64-412e-85ef-d637f92ea25f?enc=json&include_form=true&include_odds=true&include_flucs=true&include_speedmap=true&include_past_performances=true&include_form_indicators=true&include_jockey_stats=true&include_trainer_stats=true"
  },
  "params": {
    "enc": "json",
    "id": "57c7104e-3b64-412e-85ef-d637f92ea25f",
    "present_overlay": false,
    "with_big_bets": false,
    "with_live_bets": false,
    "with_money_tracker": false,
    "with_biggest_bet": false,
    "will_pays": false,
    "with_tote_trends_data": false,
    "bet_type_filter": "",
    "bets_limit": 10
  },
  "data": {
    "race": {
      "event_id": "57c7104e-3b64-412e-85ef-d637f92ea25f",
      "meeting_name": "The Gardens",
      "display_meeting_name": "The Gardens",
      "meeting_id": "07d065ff-b385-567e-9728-ec0da980abe7",
      "status": "Open",
      "description": "Tg Ladbrokes Big Bets Copy Now 6-15",
      "advertised_start": 1777723620,
      "actual_start": 1777723620,
      "advertised_start_string": "2026-05-02 12:07:00 +0000 UTC",
      "actual_start_string": "2026-05-02 12:07:00 +0000 UTC",
      "race_number": 10,
      "type": "G",
      "start_type": "",
      "country": "AUS",
      "state": "NSW",
      "distance": 400,
      "weather": "Fine",
      "form_guide": "",
      "comment": "TITAN'S OCEAN (1) was out of placings last time (23.91) at this track in a Grade 5, finishing sixth and beaten 16 lengths. Unbeaten in two runs from this draw. Looks suited and should go close. IMPERATOR (8) has been beaten for early speed lately, last time finishing fourth (23.66) in a Grade 5 at this track. Has a good record here at this journey. Warrants plenty of respect. GARY INDIANA (5) chased the lead early from the inside and boxed on well to finish third, beaten 2.5 lengths (23.30) at this track in a Grade 5 over 400m. Expected to feature again. VINNIE ZACAPA (2) should bounce back after an unplaced effort here recently.",
      "silk_base_url": "drr38safykj6s.cloudfront.net",
      "track_condition": "Good",
      "track_direction": "Left",
      "silk_url": "https://www.ladbrokes.com.au/images/sprites/greyhound-silks-standard.png",
      "entrant_count": 10,
      "positions_paid": 3,
      "video_channels": [
        "Live1"
      ],
      "video_channels_meta": {
        "Live1": {
          "RaceNo": 10,
          "RaceType": "G",
          "SlotType": "",
          "SlotTitle": "",
          "VenueName": "The Gardens",
          "CrossPoint": 143,
          "RacePriority": "1",
          "SlotDuration": "",
          "SchedulerNote": "P1 (Metropolitan)",
          "CrossPointName": "Main - TBS 03",
          "SlotDescription": "",
          "UtcRaceStartTime": "2026-05-02T12:07:00Z",
          "VenueCountryCode": "AU",
          "VenueProviderName": "GRNSW",
          "DisplayRaceStartTime": "2026-05-02T22:07:00",
          "SchedulerNotePriority": "None"
        }
      },
      "tips": [
        "efc8eee2-444d-46c3-bad5-84781a80f885",
        "d9b8c37e-cd4b-47d6-9fe7-8778ed19cc18",
        "88073ad8-26c3-45df-b242-b87af4af9f62",
        "0ac34e79-d3ac-41eb-a546-001b9b81a9d9"
      ],
      "rail_position": "",
      "group": "",
      "prize_monies": {
        "1st": 1500,
        "2nd": 435,
        "3rd": 325,
        "4th": 75,
        "total_value": 2335
      },
      "track_home_straight": 0
    },
    "favourite": {
      "entrant_id": "efc8eee2-444d-46c3-bad5-84781a80f885",
      "market_name": "Final Field",
      "primary_market": true,
      "name": "Titan's Ocean",
      "is_scratched": false,
      "gear": "",
      "best_time": "22.76",
      "odds": {
        "fixed_win": 2.05,
        "fixed_place": 1.22
      },
      "scratch_time": 0,
      "barrier": 1,
      "runner_number": 1,
      "prize_money": "7190",
      "age": 3,
      "sex": "D",
      "colour": "BL",
      "silk_colours": "",
      "silk_url_64x64": "",
      "silk_url_128x128": "",
      "form_comment": null,
      "class_level": "",
      "jockey": "",
      "apprentice_indicator": "",
      "allowance_weight": "",
      "owners": "Greg Sprod",
      "country": "AUS",
      "trainer_name": "Leeanne Goodwin",
      "last_twenty_starts": "282856x216",
      "sire": "BLACK MAGIC OPAL (AUS)",
      "dam": "PROMOTE (AUS)",
      "breeding": "d BLACK MAGIC OPAL (AUS)-PROMOTE (AUS)",
      "weight": {
        "allocated": "",
        "total": ""
      },
      "favourite": false,
      "mover": false,
      "speedmap": {
        "settling_lengths": 7,
        "entrant_id": "efc8eee2-444d-46c3-bad5-84781a80f885"
      },
      "form_indicators": [
        {
          "name": "Unbeaten from the Box",
          "group": "Track",
          "negative": false,
          "priority": 65
        }
      ],
      "past_performances": null,
      "jockey_past_performances": null,
      "trainer_location": "VERGES CREEK"
    },
    "runners": [
      {
        "entrant_id": "efc8eee2-444d-46c3-bad5-84781a80f885",
        "market_name": "Final Field",
        "primary_market": true,
        "name": "Titan's Ocean",
        "is_scratched": false,
        "gear": "",
        "best_time": "22.76",
        "odds": {
          "fixed_win": 2.05,
          "fixed_place": 1.22
        },
        "scratch_time": 0,
        "barrier": 1,
        "runner_number": 1,
        "prize_money": "7190",
        "age": 3,
        "sex": "D",
        "colour": "BL",
        "silk_colours": "",
        "silk_url_64x64": "",
        "silk_url_128x128": "",
        "form_comment": null,
        "class_level": "",
        "jockey": "",
        "apprentice_indicator": "",
        "allowance_weight": "",
        "owners": "Greg Sprod",
        "country": "AUS",
        "trainer_name": "Leeanne Goodwin",
        "last_twenty_starts": "282856x216",
        "sire": "BLACK MAGIC OPAL (AUS)",
        "dam": "PROMOTE (AUS)",
        "breeding": "d BLACK MAGIC OPAL (AUS)-PROMOTE (AUS)",
        "weight": {
          "allocated": "",
          "total": ""
        },
        "favourite": true,
        "mover": true,
        "speedmap": {
          "settling_lengths": 7,
          "entrant_id": "efc8eee2-444d-46c3-bad5-84781a80f885",
          "label": "Pace"
        },
        "form_indicators": [
          {
            "name": "Unbeaten from the Box",
            "group": "Track",
            "negative": false,
            "priority": 65
          }
        ],
        "past_performances": null,
        "jockey_past_performances": null,
        "trainer_location": "VERGES CREEK",
        "meta": null,
        "flucs": [
          2.3,
          2.35,
          1.9,
          2.2,
          2.1,
          2.05
        ],
        "scr_time": null,
        "competitor_id": "",
        "ride_guide_exists": false,
        "ride_guide_thumbnail": "",
        "ride_guide_file": "",
        "flucs_with_timestamp": {
          "last_six": [
            {
              "timestamp": "2026-05-01T23:07:14.073539755Z",
              "fluc": 2.3
            },
            {
              "timestamp": "2026-05-01T23:08:16.379669831Z",
              "fluc": 2.35
            },
            {
              "timestamp": "2026-05-01T23:08:32.638795984Z",
              "fluc": 1.9
            },
            {
              "timestamp": "2026-05-01T23:29:09.528015476Z",
              "fluc": 2.2
            },
            {
              "timestamp": "2026-05-01T23:29:49.977510253Z",
              "fluc": 2.1
            },
            {
              "timestamp": "2026-05-01T23:30:13.832390241Z",
              "fluc": 2.05
            }
          ],
          "open": {
            "timestamp": "2026-05-01T23:07:14.073539755Z",
            "fluc": 2.3
          },
          "high": {
            "timestamp": "2026-05-01T23:08:16.379669831Z",
            "fluc": 2.35
          },
          "low": {
            "timestamp": "2026-05-01T23:08:32.638795984Z",
            "fluc": 1.9
          },
          "nine_am": {
            "timestamp": "0001-01-01T00:00:00Z",
            "fluc": 0
          }
        }
      },
      {
        "entrant_id": "0ac34e79-d3ac-41eb-a546-001b9b81a9d9",
        "market_name": "Final Field",
        "primary_market": true,
        "name": "Vinnie Zacapa",
        "is_scratched": false,
        "gear": "",
        "best_time": "23.23",
        "odds": {
          "fixed_win": 9,
          "fixed_place": 2.2
        },
        "scratch_time": 0,
        "barrier": 2,
        "runner_number": 2,
        "prize_money": "1825",
        "age": 2,
        "sex": "D",
        "colour": "BDL",
        "silk_colours": "",
        "silk_url_64x64": "",
        "silk_url_128x128": "",
        "form_comment": null,
        "class_level": "",
        "jockey": "",
        "apprentice_indicator": "",
        "allowance_weight": "",
        "owners": "Troy Burton",
        "country": "AUS",
        "trainer_name": "Mischelle Edmunds",
        "last_twenty_starts": "4143454",
        "sire": "FERAL FRANKY (AUS)",
        "dam": "EPHEMERAL (AUS)",
        "breeding": "d FERAL FRANKY (AUS)-EPHEMERAL (AUS)",
        "weight": {
          "allocated": "",
          "total": ""
        },
        "favourite": false,
        "mover": false,
        "speedmap": {
          "settling_lengths": 3,
          "entrant_id": "0ac34e79-d3ac-41eb-a546-001b9b81a9d9",
          "label": "Off Midfield"
        },
        "form_indicators": null,
        "past_performances": null,
        "jockey_past_performances": null,
        "trainer_location": "SAWYERS GULLY",
        "meta": null,
        "flucs": [
          8,
          8.5,
          8,
          8.5,
          9
        ],
        "scr_time": null,
        "competitor_id": "",
        "ride_guide_exists": false,
        "ride_guide_thumbnail": "",
        "ride_guide_file": "",
        "flucs_with_timestamp": {
          "last_six": [
            {
              "timestamp": "2026-05-01T23:07:14.073527995Z",
              "fluc": 8
            },
            {
              "timestamp": "2026-05-01T23:16:38.325403003Z",
              "fluc": 8.5
            },
            {
              "timestamp": "2026-05-01T23:17:40.729204778Z",
              "fluc": 8
            },
            {
              "timestamp": "2026-05-01T23:29:09.528086538Z",
              "fluc": 8.5
            },
            {
              "timestamp": "2026-05-01T23:31:15.418654591Z",
              "fluc": 9
            }
          ],
          "open": {
            "timestamp": "2026-05-01T23:07:14.073527995Z",
            "fluc": 8
          },
          "high": {
            "timestamp": "2026-05-01T23:31:15.418654591Z",
            "fluc": 9
          },
          "low": {
            "timestamp": "2026-05-01T23:17:40.729204778Z",
            "fluc": 8
          },
          "nine_am": {
            "timestamp": "0001-01-01T00:00:00Z",
            "fluc": 0
          }
        }
      },
      {
        "entrant_id": "106834e2-9057-4be7-9dc5-e7524b13500f",
        "market_name": "Final Field",
        "primary_market": true,
        "name": "Kenny's Girl",
        "is_scratched": false,
        "gear": "",
        "best_time": "23.12",
        "odds": {
          "fixed_win": 10,
          "fixed_place": 2.3
        },
        "scratch_time": 0,
        "barrier": 3,
        "runner_number": 3,
        "prize_money": "4225",
        "age": 2,
        "sex": "B",
        "colour": "BL",
        "silk_colours": "",
        "silk_url_64x64": "",
        "silk_url_128x128": "",
        "form_comment": null,
        "class_level": "",
        "jockey": "",
        "apprentice_indicator": "",
        "allowance_weight": "",
        "owners": "Kerrie Verhagen",
        "country": "AUS",
        "trainer_name": "Stephen Bell",
        "last_twenty_starts": "x331256458",
        "sire": "BERNARDO (AUS)",
        "dam": "JULIA MULWEE (AUS)",
        "breeding": "b BERNARDO (AUS)-JULIA MULWEE (AUS)",
        "weight": {
          "allocated": "",
          "total": ""
        },
        "favourite": false,
        "mover": false,
        "speedmap": {
          "settling_lengths": 6,
          "entrant_id": "106834e2-9057-4be7-9dc5-e7524b13500f",
          "label": "Off Pace"
        },
        "form_indicators": null,
        "past_performances": null,
        "jockey_past_performances": null,
        "trainer_location": "WOODBERRY",
        "meta": null,
        "flucs": [
          9.5,
          10,
          11,
          10
        ],
        "scr_time": null,
        "competitor_id": "",
        "ride_guide_exists": false,
        "ride_guide_thumbnail": "",
        "ride_guide_file": "",
        "flucs_with_timestamp": {
          "last_six": [
            {
              "timestamp": "2026-05-01T23:07:14.07349692Z",
              "fluc": 9.5
            },
            {
              "timestamp": "2026-05-01T23:15:35.975254497Z",
              "fluc": 10
            },
            {
              "timestamp": "2026-05-01T23:29:49.97754877Z",
              "fluc": 11
            },
            {
              "timestamp": "2026-05-01T23:30:13.833033208Z",
              "fluc": 10
            }
          ],
          "open": {
            "timestamp": "2026-05-01T23:07:14.07349692Z",
            "fluc": 9.5
          },
          "high": {
            "timestamp": "2026-05-01T23:29:49.97754877Z",
            "fluc": 11
          },
          "low": {
            "timestamp": "2026-05-01T23:07:14.07349692Z",
            "fluc": 9.5
          },
          "nine_am": {
            "timestamp": "0001-01-01T00:00:00Z",
            "fluc": 0
          }
        }
      },
      {
        "entrant_id": "f068eff0-8f3c-4d27-a170-26eee766274b",
        "market_name": "Final Field",
        "primary_market": true,
        "name": "Rhonda Full Day",
        "is_scratched": false,
        "gear": "",
        "best_time": "22.97",
        "odds": {
          "fixed_win": 15,
          "fixed_place": 2.7
        },
        "scratch_time": 0,
        "barrier": 4,
        "runner_number": 4,
        "prize_money": "6390",
        "age": 2,
        "sex": "B",
        "colour": "BL",
        "silk_colours": "",
        "silk_url_64x64": "",
        "silk_url_128x128": "",
        "form_comment": null,
        "class_level": "",
        "jockey": "",
        "apprentice_indicator": "",
        "allowance_weight": "",
        "owners": "Allan Woods",
        "country": "AUS",
        "trainer_name": "Allan Woods",
        "last_twenty_starts": "4135472537",
        "sire": "TOMMY SHELBY (AUS)",
        "dam": "ELLIE BELLES (AUS)",
        "breeding": "b TOMMY SHELBY (AUS)-ELLIE BELLES (AUS)",
        "weight": {
          "allocated": "",
          "total": ""
        },
        "favourite": false,
        "mover": false,
        "speedmap": {
          "settling_lengths": 3,
          "entrant_id": "f068eff0-8f3c-4d27-a170-26eee766274b",
          "label": "Off Midfield"
        },
        "form_indicators": null,
        "past_performances": null,
        "jockey_past_performances": null,
        "trainer_location": "NABIAC",
        "meta": null,
        "flucs": [
          13,
          14,
          13,
          14,
          15
        ],
        "scr_time": null,
        "competitor_id": "",
        "ride_guide_exists": false,
        "ride_guide_thumbnail": "",
        "ride_guide_file": "",
        "flucs_with_timestamp": {
          "last_six": [
            {
              "timestamp": "2026-05-01T23:07:14.073511125Z",
              "fluc": 13
            },
            {
              "timestamp": "2026-05-01T23:09:20.772634602Z",
              "fluc": 14
            },
            {
              "timestamp": "2026-05-01T23:14:35.777509333Z",
              "fluc": 13
            },
            {
              "timestamp": "2026-05-01T23:15:35.975247791Z",
              "fluc": 14
            },
            {
              "timestamp": "2026-05-01T23:29:49.977562423Z",
              "fluc": 15
            }
          ],
          "open": {
            "timestamp": "2026-05-01T23:07:14.073511125Z",
            "fluc": 13
          },
          "high": {
            "timestamp": "2026-05-01T23:29:49.977562423Z",
            "fluc": 15
          },
          "low": {
            "timestamp": "2026-05-01T23:14:35.777509333Z",
            "fluc": 13
          },
          "nine_am": {
            "timestamp": "0001-01-01T00:00:00Z",
            "fluc": 0
          }
        }
      },
      {
        "entrant_id": "88073ad8-26c3-45df-b242-b87af4af9f62",
        "market_name": "Final Field",
        "primary_market": true,
        "name": "Gary Indiana",
        "is_scratched": false,
        "gear": "",
        "best_time": "23.03",
        "odds": {
          "fixed_win": 10,
          "fixed_place": 2.3
        },
        "scratch_time": 0,
        "barrier": 5,
        "runner_number": 5,
        "prize_money": "10870",
        "age": 2,
        "sex": "D",
        "colour": "BLU/FWN",
        "silk_colours": "",
        "silk_url_64x64": "",
        "silk_url_128x128": "",
        "form_comment": null,
        "class_level": "",
        "jockey": "",
        "apprentice_indicator": "",
        "allowance_weight": "",
        "owners": "Allan Woods",
        "country": "AUS",
        "trainer_name": "Allan Woods",
        "last_twenty_starts": "3833348343",
        "sire": "AUSSIE INFRARED (AUS)",
        "dam": "ALICE ALMIGHTY (AUS)",
        "breeding": "d AUSSIE INFRARED (AUS)-ALICE ALMIGHTY (AUS)",
        "weight": {
          "allocated": "",
          "total": ""
        },
        "favourite": false,
        "mover": false,
        "speedmap": {
          "settling_lengths": 3,
          "entrant_id": "88073ad8-26c3-45df-b242-b87af4af9f62",
          "label": "Off Midfield"
        },
        "form_indicators": null,
        "past_performances": null,
        "jockey_past_performances": null,
        "trainer_location": "NABIAC",
        "meta": null,
        "flucs": [
          9,
          9.5,
          10
        ],
        "scr_time": null,
        "competitor_id": "",
        "ride_guide_exists": false,
        "ride_guide_thumbnail": "",
        "ride_guide_file": "",
        "flucs_with_timestamp": {
          "last_six": [
            {
              "timestamp": "2026-05-01T23:07:14.073546415Z",
              "fluc": 9
            },
            {
              "timestamp": "2026-05-01T23:17:40.729186485Z",
              "fluc": 9.5
            },
            {
              "timestamp": "2026-05-01T23:29:49.977516868Z",
              "fluc": 10
            }
          ],
          "open": {
            "timestamp": "2026-05-01T23:07:14.073546415Z",
            "fluc": 9
          },
          "high": {
            "timestamp": "2026-05-01T23:29:49.977516868Z",
            "fluc": 10
          },
          "low": {
            "timestamp": "2026-05-01T23:07:14.073546415Z",
            "fluc": 9
          },
          "nine_am": {
            "timestamp": "0001-01-01T00:00:00Z",
            "fluc": 0
          }
        }
      },
      {
        "entrant_id": "edb8644a-4d49-4804-bc47-6b4aa96424e8",
        "market_name": "Final Field",
        "primary_market": true,
        "name": "Lizzie Long Legs",
        "is_scratched": false,
        "gear": "",
        "best_time": "23.21",
        "odds": {
          "fixed_win": 8.5,
          "fixed_place": 2.1
        },
        "scratch_time": 0,
        "barrier": 6,
        "runner_number": 6,
        "prize_money": "14560",
        "age": 3,
        "sex": "B",
        "colour": "BDL",
        "silk_colours": "",
        "silk_url_64x64": "",
        "silk_url_128x128": "",
        "form_comment": null,
        "class_level": "",
        "jockey": "",
        "apprentice_indicator": "",
        "allowance_weight": "",
        "owners": "Andrew Bell",
        "country": "AUS",
        "trainer_name": "Andrew Bell",
        "last_twenty_starts": "1335265725",
        "sire": "DJAYS OCTANE (USA)",
        "dam": "PRODIGIOUS (AUS)",
        "breeding": "b DJAYS OCTANE (USA)-PRODIGIOUS (AUS)",
        "weight": {
          "allocated": "",
          "total": ""
        },
        "favourite": false,
        "mover": false,
        "speedmap": {
          "settling_lengths": 3,
          "entrant_id": "edb8644a-4d49-4804-bc47-6b4aa96424e8",
          "label": "Off Midfield"
        },
        "form_indicators": null,
        "past_performances": null,
        "jockey_past_performances": null,
        "trainer_location": "WEROMBI",
        "meta": null,
        "flucs": [
          8,
          8.5
        ],
        "scr_time": null,
        "competitor_id": "",
        "ride_guide_exists": false,
        "ride_guide_thumbnail": "",
        "ride_guide_file": "",
        "flucs_with_timestamp": {
          "last_six": [
            {
              "timestamp": "2026-05-01T23:07:14.073480942Z",
              "fluc": 8
            },
            {
              "timestamp": "2026-05-01T23:15:35.975287225Z",
              "fluc": 8.5
            }
          ],
          "open": {
            "timestamp": "2026-05-01T23:07:14.073480942Z",
            "fluc": 8
          },
          "high": {
            "timestamp": "2026-05-01T23:15:35.975287225Z",
            "fluc": 8.5
          },
          "low": {
            "timestamp": "2026-05-01T23:07:14.073480942Z",
            "fluc": 8
          },
          "nine_am": {
            "timestamp": "0001-01-01T00:00:00Z",
            "fluc": 0
          }
        }
      },
      {
        "entrant_id": "c952d36e-cb52-4cab-96f8-0c0348755941",
        "market_name": "Final Field",
        "primary_market": true,
        "name": "Hot To Rule",
        "is_scratched": false,
        "gear": "",
        "best_time": "22.98",
        "odds": {
          "fixed_win": 7,
          "fixed_place": 1.95
        },
        "scratch_time": 0,
        "barrier": 7,
        "runner_number": 7,
        "prize_money": "2720",
        "age": 2,
        "sex": "D",
        "colour": "BDL",
        "silk_colours": "",
        "silk_url_64x64": "",
        "silk_url_128x128": "",
        "form_comment": null,
        "class_level": "",
        "jockey": "",
        "apprentice_indicator": "",
        "allowance_weight": "",
        "owners": "Greg Ford",
        "country": "AUS",
        "trainer_name": "Greg Ford",
        "last_twenty_starts": "55x1236326",
        "sire": "SIMPLY LIMELIGHT (AUS)",
        "dam": "SET TO REIGN (AUS)",
        "breeding": "d SIMPLY LIMELIGHT (AUS)-SET TO REIGN (AUS)",
        "weight": {
          "allocated": "",
          "total": ""
        },
        "favourite": false,
        "mover": false,
        "speedmap": {
          "settling_lengths": 4,
          "entrant_id": "c952d36e-cb52-4cab-96f8-0c0348755941",
          "label": "Midfield"
        },
        "form_indicators": null,
        "past_performances": null,
        "jockey_past_performances": null,
        "trainer_location": "ASHTONFIELD",
        "meta": null,
        "flucs": [
          6.5,
          7
        ],
        "scr_time": null,
        "competitor_id": "",
        "ride_guide_exists": false,
        "ride_guide_thumbnail": "",
        "ride_guide_file": "",
        "flucs_with_timestamp": {
          "last_six": [
            {
              "timestamp": "2026-05-01T23:07:14.073511247Z",
              "fluc": 6.5
            },
            {
              "timestamp": "2026-05-01T23:29:49.977528168Z",
              "fluc": 7
            }
          ],
          "open": {
            "timestamp": "2026-05-01T23:07:14.073511247Z",
            "fluc": 6.5
          },
          "high": {
            "timestamp": "2026-05-01T23:29:49.977528168Z",
            "fluc": 7
          },
          "low": {
            "timestamp": "2026-05-01T23:07:14.073511247Z",
            "fluc": 6.5
          },
          "nine_am": {
            "timestamp": "0001-01-01T00:00:00Z",
            "fluc": 0
          }
        }
      },
      {
        "entrant_id": "d9b8c37e-cd4b-47d6-9fe7-8778ed19cc18",
        "market_name": "Final Field",
        "primary_market": true,
        "name": "Imperator",
        "is_scratched": false,
        "gear": "",
        "best_time": "22.73",
        "odds": {
          "fixed_win": 4.4,
          "fixed_place": 1.6
        },
        "scratch_time": 0,
        "barrier": 8,
        "runner_number": 8,
        "prize_money": "5860",
        "age": 3,
        "sex": "B",
        "colour": "BL",
        "silk_colours": "",
        "silk_url_64x64": "",
        "silk_url_128x128": "",
        "form_comment": null,
        "class_level": "",
        "jockey": "",
        "apprentice_indicator": "",
        "allowance_weight": "",
        "owners": "Maher Maher Synd D Maher,P Maher",
        "country": "AUS",
        "trainer_name": "Christopher Kedwell",
        "last_twenty_starts": "36x4732264",
        "sire": "BEAST UNLEASHED (AUS)",
        "dam": "MIDNIGHT SEA (AUS)",
        "breeding": "b BEAST UNLEASHED (AUS)-MIDNIGHT SEA (AUS)",
        "weight": {
          "allocated": "",
          "total": ""
        },
        "favourite": false,
        "mover": false,
        "speedmap": {
          "settling_lengths": 4,
          "entrant_id": "d9b8c37e-cd4b-47d6-9fe7-8778ed19cc18",
          "label": "Midfield"
        },
        "form_indicators": null,
        "past_performances": null,
        "jockey_past_performances": null,
        "trainer_location": "ELRINGTON",
        "meta": null,
        "flucs": [
          4.4,
          4.2,
          4.4,
          4.5,
          4.4
        ],
        "scr_time": null,
        "competitor_id": "",
        "ride_guide_exists": false,
        "ride_guide_thumbnail": "",
        "ride_guide_file": "",
        "flucs_with_timestamp": {
          "last_six": [
            {
              "timestamp": "2026-05-01T23:07:14.073474548Z",
              "fluc": 4.4
            },
            {
              "timestamp": "2026-05-01T23:16:38.325393111Z",
              "fluc": 4.2
            },
            {
              "timestamp": "2026-05-01T23:29:49.977551277Z",
              "fluc": 4.4
            },
            {
              "timestamp": "2026-05-01T23:30:13.832999033Z",
              "fluc": 4.5
            },
            {
              "timestamp": "2026-05-01T23:33:22.82597351Z",
              "fluc": 4.4
            }
          ],
          "open": {
            "timestamp": "2026-05-01T23:07:14.073474548Z",
            "fluc": 4.4
          },
          "high": {
            "timestamp": "2026-05-01T23:30:13.832999033Z",
            "fluc": 4.5
          },
          "low": {
            "timestamp": "2026-05-01T23:16:38.325393111Z",
            "fluc": 4.2
          },
          "nine_am": {
            "timestamp": "0001-01-01T00:00:00Z",
            "fluc": 0
          }
        }
      },
      {
        "entrant_id": "d726bdd9-354b-41a1-83b6-8a2c2afe734f",
        "market_name": "Final Field",
        "primary_market": true,
        "name": "Fantastic Maxine",
        "is_scratched": true,
        "gear": "",
        "best_time": "23.59",
        "odds": {
          "fixed_win": 0,
          "fixed_place": 0
        },
        "scratch_time": 1777674472,
        "barrier": 0,
        "runner_number": 9,
        "prize_money": "4035",
        "age": 3,
        "sex": "B",
        "colour": "BDL",
        "silk_colours": "",
        "silk_url_64x64": "",
        "silk_url_128x128": "",
        "form_comment": null,
        "class_level": "",
        "jockey": "",
        "apprentice_indicator": "",
        "allowance_weight": "",
        "owners": "Andrew Bell",
        "country": "AUS",
        "trainer_name": "Andrew Bell",
        "last_twenty_starts": "8864877767",
        "sire": "FERNANDO BALE (AUS)",
        "dam": "FANTASTIC SHELL (AUS)",
        "breeding": "b FERNANDO BALE (AUS)-FANTASTIC SHELL (AUS)",
        "weight": {
          "allocated": "",
          "total": ""
        },
        "favourite": false,
        "mover": false,
        "speedmap": {
          "settling_lengths": 1,
          "entrant_id": "d726bdd9-354b-41a1-83b6-8a2c2afe734f",
          "label": "invalid settling lengths"
        },
        "form_indicators": null,
        "past_performances": null,
        "jockey_past_performances": null,
        "trainer_location": "WEROMBI",
        "meta": null,
        "flucs": [],
        "scr_time": "2026-05-01T22:27:52Z",
        "competitor_id": "",
        "ride_guide_exists": false,
        "ride_guide_thumbnail": "",
        "ride_guide_file": "",
        "flucs_with_timestamp": {
          "last_six": [],
          "open": {
            "timestamp": "0001-01-01T00:00:00Z",
            "fluc": 0
          },
          "high": {
            "timestamp": "0001-01-01T00:00:00Z",
            "fluc": 0
          },
          "low": {
            "timestamp": "0001-01-01T00:00:00Z",
            "fluc": 0
          },
          "nine_am": {
            "timestamp": "0001-01-01T00:00:00Z",
            "fluc": 0
          }
        }
      },
      {
        "entrant_id": "7b146b39-3d42-423d-94af-a0e89f6da5e4",
        "market_name": "Final Field",
        "primary_market": true,
        "name": "Miracle Jack",
        "is_scratched": true,
        "gear": "",
        "best_time": "23.62",
        "odds": {
          "fixed_win": 0,
          "fixed_place": 0
        },
        "scratch_time": 1777674473,
        "barrier": 0,
        "runner_number": 10,
        "prize_money": "1070",
        "age": 1,
        "sex": "D",
        "colour": "BL",
        "silk_colours": "",
        "silk_url_64x64": "",
        "silk_url_128x128": "",
        "form_comment": null,
        "class_level": "",
        "jockey": "",
        "apprentice_indicator": "",
        "allowance_weight": "",
        "owners": "Todd Dunn",
        "country": "AUS",
        "trainer_name": "Beverley Sloan",
        "last_twenty_starts": "6737667886",
        "sire": "BEAST UNLEASHED (AUS)",
        "dam": "MISS MAPLE (AUS)",
        "breeding": "d BEAST UNLEASHED (AUS)-MISS MAPLE (AUS)",
        "weight": {
          "allocated": "",
          "total": ""
        },
        "favourite": false,
        "mover": false,
        "speedmap": {
          "settling_lengths": 1,
          "entrant_id": "7b146b39-3d42-423d-94af-a0e89f6da5e4",
          "label": "invalid settling lengths"
        },
        "form_indicators": null,
        "past_performances": null,
        "jockey_past_performances": null,
        "trainer_location": "ERARING",
        "meta": null,
        "flucs": [],
        "scr_time": "2026-05-01T22:27:53Z",
        "competitor_id": "",
        "ride_guide_exists": false,
        "ride_guide_thumbnail": "",
        "ride_guide_file": "",
        "flucs_with_timestamp": {
          "last_six": [],
          "open": {
            "timestamp": "0001-01-01T00:00:00Z",
            "fluc": 0
          },
          "high": {
            "timestamp": "0001-01-01T00:00:00Z",
            "fluc": 0
          },
          "low": {
            "timestamp": "0001-01-01T00:00:00Z",
            "fluc": 0
          },
          "nine_am": {
            "timestamp": "0001-01-01T00:00:00Z",
            "fluc": 0
          }
        }
      }
    ],
    "derivatives": null,
    "mover": {
      "entrant_id": "efc8eee2-444d-46c3-bad5-84781a80f885",
      "market_name": "Final Field",
      "primary_market": true,
      "name": "Titan's Ocean",
      "is_scratched": false,
      "gear": "",
      "best_time": "22.76",
      "odds": {
        "fixed_win": 2.05,
        "fixed_place": 1.22
      },
      "scratch_time": 0,
      "barrier": 1,
      "runner_number": 1,
      "prize_money": "7190",
      "age": 3,
      "sex": "D",
      "colour": "BL",
      "silk_colours": "",
      "silk_url_64x64": "",
      "silk_url_128x128": "",
      "form_comment": null,
      "class_level": "",
      "jockey": "",
      "apprentice_indicator": "",
      "allowance_weight": "",
      "owners": "Greg Sprod",
      "country": "AUS",
      "trainer_name": "Leeanne Goodwin",
      "last_twenty_starts": "282856x216",
      "sire": "BLACK MAGIC OPAL (AUS)",
      "dam": "PROMOTE (AUS)",
      "breeding": "d BLACK MAGIC OPAL (AUS)-PROMOTE (AUS)",
      "weight": {
        "allocated": "",
        "total": ""
      },
      "favourite": false,
      "mover": true,
      "speedmap": {
        "settling_lengths": 7,
        "entrant_id": "efc8eee2-444d-46c3-bad5-84781a80f885"
      },
      "form_indicators": [
        {
          "name": "Unbeaten from the Box",
          "group": "Track",
          "negative": false,
          "priority": 65
        }
      ],
      "past_performances": null,
      "jockey_past_performances": null,
      "trainer_location": "VERGES CREEK"
    },
    "big_bets": null,
    "live_bets": null,
    "biggest_bet": null,
    "money_tracker": null,
    "error": ""
  }
}