{
  "header": {
    "title": "Event Details: fb5a7da6-0641-4cc7-8842-4ad348fa6e0a",
    "generated_time": "2026-01-15T23:43:26.36224506Z",
    "url": "/affiliates/v1/racing/events/fb5a7da6-0641-4cc7-8842-4ad348fa6e0a?enc=json&include_form=true&include_odds=true&include_flucs=true&include_speedmap=true&include_past_performances=true&include_form_indicators=true&include_jockey_stats=true&include_trainer_stats=true"
  },
  "params": {
    "enc": "json",
    "id": "fb5a7da6-0641-4cc7-8842-4ad348fa6e0a",
    "present_overlay": false,
    "with_big_bets": false,
    "with_live_bets": false,
    "with_money_tracker": false,
    "with_biggest_bet": false,
    "will_pays": false,
    "with_tote_trends_data": false,
    "bet_type_filter": "",
    "bets_limit": 10
  },
  "data": {
    "race": {
      "event_id": "fb5a7da6-0641-4cc7-8842-4ad348fa6e0a",
      "meeting_name": "Q1 Lakeside",
      "display_meeting_name": "Q1 Lakeside",
      "meeting_id": "e6d12bf8-4f93-4d53-ba9e-3d5fbb7e5711",
      "status": "Open",
      "description": "Rosewood Veterinary Service 5Th Grade H",
      "advertised_start": 1768545120,
      "actual_start": 1768545120,
      "advertised_start_string": "2026-01-16 06:32:00 +0000 UTC",
      "actual_start_string": "2026-01-16 06:32:00 +0000 UTC",
      "race_number": 8,
      "type": "G",
      "start_type": "",
      "country": "AUS",
      "state": "QLD",
      "distance": 390,
      "weather": "overcast",
      "form_guide": "",
      "comment": "NEXT BLACK JACK (8) steps out for the first time at this track. In the money last start when third (24.12) at Rockhampton over 407m. The form from his last run stacks up well. Makes plenty of appeal. KICKIN' TYRES (2) has missed the frame at last two runs but could not have been more impressive a few back in his lightning 16.30 win at Q Straight over 300m. Should be in this for a long way. NON STOP WHISKEY (6) boasts a strong record this journey here with three wins and three minors from eight tries. Recorded a 4.5 lengths win (21.53) in a Grade 5 last time at this track. Can hit the frame with the right run. TUSKEN RAIDER (5) is on a run of three wins – must be respected.",
      "silk_base_url": "drr38safykj6s.cloudfront.net",
      "track_condition": "Good",
      "track_direction": "Left",
      "silk_url": "https://www.ladbrokes.com.au/images/sprites/greyhound-silks-standard.png",
      "entrant_count": 10,
      "positions_paid": 3,
      "video_channels": [
        "Live2"
      ],
      "video_channels_meta": {
        "Live2": {
          "RaceNo": 8,
          "RaceType": "G",
          "SlotType": "",
          "SlotTitle": "",
          "VenueName": "Q1 Lakeside",
          "CrossPoint": 21,
          "RacePriority": "2",
          "SlotDuration": "",
          "SchedulerNote": "Metro *Please join Waterlea R12 post race ASAP*",
          "CrossPointName": "SKY 02",
          "SlotDescription": "",
          "UtcRaceStartTime": "2026-01-16T06:34:00Z",
          "VenueCountryCode": "AU",
          "VenueProviderName": "SKY",
          "DisplayRaceStartTime": "2026-01-16T16:34:00",
          "SchedulerNotePriority": "Information"
        }
      },
      "tips": [
        "e636e269-a0e9-4ff0-989a-0e5b62563898",
        "29e0905e-47e3-4f60-9f18-f6d850bb3352",
        "535e3e64-75b2-42ec-a3f2-e886921dc369",
        "6785c40c-28e5-45d3-807c-83a68d699755"
      ],
      "rail_position": "",
      "group": "",
      "prize_monies": {
        "1st": 1950,
        "2nd": 600,
        "3rd": 300,
        "4th": 150,
        "total_value": 3000
      },
      "track_home_straight": 0
    },
    "favourite": {
      "entrant_id": "535e3e64-75b2-42ec-a3f2-e886921dc369",
      "market_name": "Final Field",
      "primary_market": true,
      "name": "Non Stop Whiskey",
      "is_scratched": false,
      "gear": "",
      "best_time": "21.53",
      "odds": {
        "fixed_win": 1.6,
        "fixed_place": 1.09
      },
      "scratch_time": 0,
      "barrier": 6,
      "runner_number": 6,
      "prize_money": "13105",
      "age": 2,
      "sex": "D",
      "colour": "FWN",
      "silk_colours": "",
      "silk_url_64x64": "",
      "silk_url_128x128": "",
      "form_comment": null,
      "class_level": "",
      "jockey": "",
      "apprentice_indicator": "",
      "allowance_weight": "",
      "owners": "Non-Stop Pings Racing Synd A Poulter,P Bannister,A Harwood",
      "country": "AUS",
      "trainer_name": "Jamie Hosking",
      "last_twenty_starts": "22467x1321",
      "sire": "FERNANDO BALE (AUS)",
      "dam": "MICKS RECALL (AUS)",
      "breeding": "d FERNANDO BALE (AUS)-MICKS RECALL (AUS)",
      "weight": {
        "allocated": "",
        "total": ""
      },
      "favourite": false,
      "mover": false,
      "speedmap": {
        "settling_lengths": 7,
        "entrant_id": "535e3e64-75b2-42ec-a3f2-e886921dc369"
      },
      "form_indicators": [
        {
          "name": "Dominant Win Last Start",
          "group": "Last_Start_Winner",
          "negative": false,
          "priority": 150
        }
      ],
      "past_performances": null,
      "jockey_past_performances": null,
      "trainer_location": "Churchable"
    },
    "runners": [
      {
        "entrant_id": "dbe36955-b5c7-40d9-bf26-96f5782b3956",
        "market_name": "Final Field",
        "primary_market": true,
        "name": "Peppimenarti",
        "is_scratched": false,
        "gear": "",
        "best_time": "22.08",
        "odds": {
          "fixed_win": 19,
          "fixed_place": 2.6
        },
        "scratch_time": 0,
        "barrier": 1,
        "runner_number": 1,
        "prize_money": "5150",
        "age": 2,
        "sex": "D",
        "colour": "BL",
        "silk_colours": "",
        "silk_url_64x64": "",
        "silk_url_128x128": "",
        "form_comment": null,
        "class_level": "",
        "jockey": "",
        "apprentice_indicator": "",
        "allowance_weight": "",
        "owners": "Kerry Hoggan",
        "country": "AUS",
        "trainer_name": "Kerry Hoggan",
        "last_twenty_starts": "3633421717",
        "sire": "EQUALIZER (AUS)",
        "dam": "WYNNUM STAR (AUS)",
        "breeding": "d EQUALIZER (AUS)-WYNNUM STAR (AUS)",
        "weight": {
          "allocated": "",
          "total": ""
        },
        "favourite": false,
        "mover": true,
        "speedmap": {
          "settling_lengths": 4,
          "entrant_id": "dbe36955-b5c7-40d9-bf26-96f5782b3956",
          "label": "Midfield"
        },
        "form_indicators": null,
        "past_performances": null,
        "jockey_past_performances": null,
        "trainer_location": "CHURCHABLE",
        "meta": null,
        "flucs": [
          27,
          21,
          19
        ],
        "scr_time": null,
        "competitor_id": "",
        "ride_guide_exists": false,
        "ride_guide_thumbnail": "",
        "ride_guide_file": "",
        "flucs_with_timestamp": {
          "last_six": [
            {
              "timestamp": "2026-01-15T22:06:21.293266094Z",
              "fluc": 27
            },
            {
              "timestamp": "2026-01-15T23:29:35.037569453Z",
              "fluc": 21
            },
            {
              "timestamp": "2026-01-15T23:38:29.889624164Z",
              "fluc": 19
            }
          ],
          "open": {
            "timestamp": "2026-01-15T22:06:21.293266094Z",
            "fluc": 27
          },
          "high": {
            "timestamp": "2026-01-15T22:06:21.293266094Z",
            "fluc": 27
          },
          "low": {
            "timestamp": "2026-01-15T23:38:29.889624164Z",
            "fluc": 19
          },
          "nine_am": {
            "timestamp": "0001-01-01T00:00:00Z",
            "fluc": 0
          }
        }
      },
      {
        "entrant_id": "29e0905e-47e3-4f60-9f18-f6d850bb3352",
        "market_name": "Final Field",
        "primary_market": true,
        "name": "Kickin' Tyres",
        "is_scratched": false,
        "gear": "",
        "best_time": "21.68",
        "odds": {
          "fixed_win": 5,
          "fixed_place": 1.5
        },
        "scratch_time": 0,
        "barrier": 2,
        "runner_number": 2,
        "prize_money": "15305",
        "age": 3,
        "sex": "D",
        "colour": "BL",
        "silk_colours": "",
        "silk_url_64x64": "",
        "silk_url_128x128": "",
        "form_comment": null,
        "class_level": "",
        "jockey": "",
        "apprentice_indicator": "",
        "allowance_weight": "",
        "owners": "Todd Wiegand",
        "country": "AUS",
        "trainer_name": "Merv Page",
        "last_twenty_starts": "1232311145",
        "sire": "KOBLENZ (AUS)",
        "dam": "SAPPHIRE QUEEN (AUS)",
        "breeding": "d KOBLENZ (AUS)-SAPPHIRE QUEEN (AUS)",
        "weight": {
          "allocated": "",
          "total": ""
        },
        "favourite": false,
        "mover": false,
        "speedmap": {
          "settling_lengths": 7,
          "entrant_id": "29e0905e-47e3-4f60-9f18-f6d850bb3352",
          "label": "Midfield"
        },
        "form_indicators": [
          {
            "name": "Track / Distance Specialist",
            "group": "Track_Distance",
            "negative": false,
            "priority": 60
          }
        ],
        "past_performances": null,
        "jockey_past_performances": null,
        "trainer_location": "Walloon",
        "meta": null,
        "flucs": [
          5
        ],
        "scr_time": null,
        "competitor_id": "",
        "ride_guide_exists": false,
        "ride_guide_thumbnail": "",
        "ride_guide_file": "",
        "flucs_with_timestamp": {
          "last_six": [
            {
              "timestamp": "2026-01-15T22:06:21.293377056Z",
              "fluc": 5
            }
          ],
          "open": {
            "timestamp": "2026-01-15T22:06:21.293377056Z",
            "fluc": 5
          },
          "high": {
            "timestamp": "2026-01-15T22:06:21.293377056Z",
            "fluc": 5
          },
          "low": {
            "timestamp": "2026-01-15T22:06:21.293377056Z",
            "fluc": 5
          },
          "nine_am": {
            "timestamp": "0001-01-01T00:00:00Z",
            "fluc": 0
          }
        }
      },
      {
        "entrant_id": "1959aba9-5c63-4775-9bef-7d2464864460",
        "market_name": "Final Field",
        "primary_market": true,
        "name": "Turbo Tully",
        "is_scratched": false,
        "gear": "",
        "best_time": "22.29",
        "odds": {
          "fixed_win": 31,
          "fixed_place": 3.2
        },
        "scratch_time": 0,
        "barrier": 3,
        "runner_number": 3,
        "prize_money": "11140",
        "age": 2,
        "sex": "B",
        "colour": "W/BL",
        "silk_colours": "",
        "silk_url_64x64": "",
        "silk_url_128x128": "",
        "form_comment": null,
        "class_level": "",
        "jockey": "",
        "apprentice_indicator": "",
        "allowance_weight": "",
        "owners": "Greg Short",
        "country": "AUS",
        "trainer_name": "Anthony Short",
        "last_twenty_starts": "3661624755",
        "sire": "KOBLENZ (AUS)",
        "dam": "MUSTANG TULLY (AUS)",
        "breeding": "b KOBLENZ (AUS)-MUSTANG TULLY (AUS)",
        "weight": {
          "allocated": "",
          "total": ""
        },
        "favourite": false,
        "mover": false,
        "speedmap": {
          "settling_lengths": 5,
          "entrant_id": "1959aba9-5c63-4775-9bef-7d2464864460",
          "label": "Midfield"
        },
        "form_indicators": null,
        "past_performances": null,
        "jockey_past_performances": null,
        "trainer_location": "Seventeen Mile Rocks",
        "meta": null,
        "flucs": [
          41,
          34,
          31
        ],
        "scr_time": null,
        "competitor_id": "",
        "ride_guide_exists": false,
        "ride_guide_thumbnail": "",
        "ride_guide_file": "",
        "flucs_with_timestamp": {
          "last_six": [
            {
              "timestamp": "2026-01-15T22:06:21.293248556Z",
              "fluc": 41
            },
            {
              "timestamp": "2026-01-15T23:30:48.537734775Z",
              "fluc": 34
            },
            {
              "timestamp": "2026-01-15T23:38:29.889601Z",
              "fluc": 31
            }
          ],
          "open": {
            "timestamp": "2026-01-15T22:06:21.293248556Z",
            "fluc": 41
          },
          "high": {
            "timestamp": "2026-01-15T22:06:21.293248556Z",
            "fluc": 41
          },
          "low": {
            "timestamp": "2026-01-15T23:38:29.889601Z",
            "fluc": 31
          },
          "nine_am": {
            "timestamp": "0001-01-01T00:00:00Z",
            "fluc": 0
          }
        }
      },
      {
        "entrant_id": "51109a77-b410-49d0-80e2-8eb77898940d",
        "market_name": "Final Field",
        "primary_market": true,
        "name": "Spring Toulon",
        "is_scratched": false,
        "gear": "",
        "best_time": "22.07",
        "odds": {
          "fixed_win": 51,
          "fixed_place": 4
        },
        "scratch_time": 0,
        "barrier": 4,
        "runner_number": 4,
        "prize_money": "5600",
        "age": 2,
        "sex": "B",
        "colour": "BL",
        "silk_colours": "",
        "silk_url_64x64": "",
        "silk_url_128x128": "",
        "form_comment": null,
        "class_level": "",
        "jockey": "",
        "apprentice_indicator": "",
        "allowance_weight": "",
        "owners": "Scott Board",
        "country": "AUS",
        "trainer_name": "Pauline Byers",
        "last_twenty_starts": "4774178637",
        "sire": "ASTON RUPEE (AUS)",
        "dam": "TIES THAT BIND (AUS)",
        "breeding": "b ASTON RUPEE (AUS)-TIES THAT BIND (AUS)",
        "weight": {
          "allocated": "",
          "total": ""
        },
        "favourite": false,
        "mover": false,
        "speedmap": {
          "settling_lengths": 5,
          "entrant_id": "51109a77-b410-49d0-80e2-8eb77898940d",
          "label": "Midfield"
        },
        "form_indicators": null,
        "past_performances": null,
        "jockey_past_performances": null,
        "trainer_location": "Drayton",
        "meta": null,
        "flucs": [
          41,
          46,
          51
        ],
        "scr_time": null,
        "competitor_id": "",
        "ride_guide_exists": false,
        "ride_guide_thumbnail": "",
        "ride_guide_file": "",
        "flucs_with_timestamp": {
          "last_six": [
            {
              "timestamp": "2026-01-15T22:06:21.293211307Z",
              "fluc": 41
            },
            {
              "timestamp": "2026-01-15T23:30:48.537710167Z",
              "fluc": 46
            },
            {
              "timestamp": "2026-01-15T23:38:29.889636675Z",
              "fluc": 51
            }
          ],
          "open": {
            "timestamp": "2026-01-15T22:06:21.293211307Z",
            "fluc": 41
          },
          "high": {
            "timestamp": "2026-01-15T23:38:29.889636675Z",
            "fluc": 51
          },
          "low": {
            "timestamp": "2026-01-15T22:06:21.293211307Z",
            "fluc": 41
          },
          "nine_am": {
            "timestamp": "0001-01-01T00:00:00Z",
            "fluc": 0
          }
        }
      },
      {
        "entrant_id": "6785c40c-28e5-45d3-807c-83a68d699755",
        "market_name": "Final Field",
        "primary_market": true,
        "name": "Tusken Raider",
        "is_scratched": false,
        "gear": "",
        "best_time": "NBT",
        "odds": {
          "fixed_win": 4.2,
          "fixed_place": 1.4
        },
        "scratch_time": 0,
        "barrier": 5,
        "runner_number": 5,
        "prize_money": "12500",
        "age": 1,
        "sex": "D",
        "colour": "BL",
        "silk_colours": "",
        "silk_url_64x64": "",
        "silk_url_128x128": "",
        "form_comment": null,
        "class_level": "",
        "jockey": "",
        "apprentice_indicator": "",
        "allowance_weight": "",
        "owners": "Phillip Sear",
        "country": "AUS",
        "trainer_name": "Phillip Sear",
        "last_twenty_starts": "5626415111",
        "sire": "AUSSIE INFRARED (AUS)",
        "dam": "ZIP STREAM (AUS)",
        "breeding": "d AUSSIE INFRARED (AUS)-ZIP STREAM (AUS)",
        "weight": {
          "allocated": "",
          "total": ""
        },
        "favourite": false,
        "mover": false,
        "speedmap": {
          "settling_lengths": 8,
          "entrant_id": "6785c40c-28e5-45d3-807c-83a68d699755",
          "label": "Front Runner"
        },
        "form_indicators": [
          {
            "name": "Picket Fence",
            "group": "Last_Start_Winner",
            "negative": false,
            "priority": 220
          },
          {
            "name": "Dominant Win Last Start",
            "group": "Last_Start_Winner",
            "negative": false,
            "priority": 150
          },
          {
            "name": "Box Specialist",
            "group": "Box_History",
            "negative": false,
            "priority": 70
          }
        ],
        "past_performances": null,
        "jockey_past_performances": null,
        "trainer_location": "Kawana",
        "meta": null,
        "flucs": [
          4,
          4.2
        ],
        "scr_time": null,
        "competitor_id": "",
        "ride_guide_exists": false,
        "ride_guide_thumbnail": "",
        "ride_guide_file": "",
        "flucs_with_timestamp": {
          "last_six": [
            {
              "timestamp": "2026-01-15T22:06:21.293272427Z",
              "fluc": 4
            },
            {
              "timestamp": "2026-01-15T23:30:48.537723127Z",
              "fluc": 4.2
            }
          ],
          "open": {
            "timestamp": "2026-01-15T22:06:21.293272427Z",
            "fluc": 4
          },
          "high": {
            "timestamp": "2026-01-15T23:30:48.537723127Z",
            "fluc": 4.2
          },
          "low": {
            "timestamp": "2026-01-15T22:06:21.293272427Z",
            "fluc": 4
          },
          "nine_am": {
            "timestamp": "0001-01-01T00:00:00Z",
            "fluc": 0
          }
        }
      },
      {
        "entrant_id": "535e3e64-75b2-42ec-a3f2-e886921dc369",
        "market_name": "Final Field",
        "primary_market": true,
        "name": "Non Stop Whiskey",
        "is_scratched": false,
        "gear": "",
        "best_time": "21.53",
        "odds": {
          "fixed_win": 1.6,
          "fixed_place": 1.09
        },
        "scratch_time": 0,
        "barrier": 6,
        "runner_number": 6,
        "prize_money": "13105",
        "age": 2,
        "sex": "D",
        "colour": "FWN",
        "silk_colours": "",
        "silk_url_64x64": "",
        "silk_url_128x128": "",
        "form_comment": null,
        "class_level": "",
        "jockey": "",
        "apprentice_indicator": "",
        "allowance_weight": "",
        "owners": "Non-Stop Pings Racing Synd A Poulter,P Bannister,A Harwood",
        "country": "AUS",
        "trainer_name": "Jamie Hosking",
        "last_twenty_starts": "22467x1321",
        "sire": "FERNANDO BALE (AUS)",
        "dam": "MICKS RECALL (AUS)",
        "breeding": "d FERNANDO BALE (AUS)-MICKS RECALL (AUS)",
        "weight": {
          "allocated": "",
          "total": ""
        },
        "favourite": true,
        "mover": false,
        "speedmap": {
          "settling_lengths": 7,
          "entrant_id": "535e3e64-75b2-42ec-a3f2-e886921dc369",
          "label": "Midfield"
        },
        "form_indicators": [
          {
            "name": "Dominant Win Last Start",
            "group": "Last_Start_Winner",
            "negative": false,
            "priority": 150
          }
        ],
        "past_performances": null,
        "jockey_past_performances": null,
        "trainer_location": "Churchable",
        "meta": null,
        "flucs": [
          1.55,
          1.6
        ],
        "scr_time": null,
        "competitor_id": "",
        "ride_guide_exists": false,
        "ride_guide_thumbnail": "",
        "ride_guide_file": "",
        "flucs_with_timestamp": {
          "last_six": [
            {
              "timestamp": "2026-01-15T22:06:21.293239972Z",
              "fluc": 1.55
            },
            {
              "timestamp": "2026-01-15T22:14:06.789089224Z",
              "fluc": 1.6
            }
          ],
          "open": {
            "timestamp": "2026-01-15T22:06:21.293239972Z",
            "fluc": 1.55
          },
          "high": {
            "timestamp": "2026-01-15T22:14:06.789089224Z",
            "fluc": 1.6
          },
          "low": {
            "timestamp": "2026-01-15T22:06:21.293239972Z",
            "fluc": 1.55
          },
          "nine_am": {
            "timestamp": "0001-01-01T00:00:00Z",
            "fluc": 0
          }
        }
      },
      {
        "entrant_id": "d27afcac-ed95-45e9-bb32-bf29eba561fa",
        "market_name": "Final Field",
        "primary_market": true,
        "name": "Hara's Fonzie",
        "is_scratched": false,
        "gear": "",
        "best_time": "NBT",
        "odds": {
          "fixed_win": 27,
          "fixed_place": 3.1
        },
        "scratch_time": 0,
        "barrier": 7,
        "runner_number": 7,
        "prize_money": "16230",
        "age": 3,
        "sex": "D",
        "colour": "BL",
        "silk_colours": "",
        "silk_url_64x64": "",
        "silk_url_128x128": "",
        "form_comment": null,
        "class_level": "",
        "jockey": "",
        "apprentice_indicator": "",
        "allowance_weight": "",
        "owners": "Kylie Raines",
        "country": "AUS",
        "trainer_name": "Kylie Raines",
        "last_twenty_starts": "1452471555",
        "sire": "SHIMA SHINE (AUS)",
        "dam": "HARA'S INDI (AUS)",
        "breeding": "d SHIMA SHINE (AUS)-HARA'S INDI (AUS)",
        "weight": {
          "allocated": "",
          "total": ""
        },
        "favourite": false,
        "mover": false,
        "speedmap": {
          "settling_lengths": 3,
          "entrant_id": "d27afcac-ed95-45e9-bb32-bf29eba561fa",
          "label": "Back Marker"
        },
        "form_indicators": null,
        "past_performances": null,
        "jockey_past_performances": null,
        "trainer_location": "Redbank Plains",
        "meta": null,
        "flucs": [
          27
        ],
        "scr_time": null,
        "competitor_id": "",
        "ride_guide_exists": false,
        "ride_guide_thumbnail": "",
        "ride_guide_file": "",
        "flucs_with_timestamp": {
          "last_six": [
            {
              "timestamp": "2026-01-15T22:06:21.293204989Z",
              "fluc": 27
            }
          ],
          "open": {
            "timestamp": "2026-01-15T22:06:21.293204989Z",
            "fluc": 27
          },
          "high": {
            "timestamp": "2026-01-15T22:06:21.293204989Z",
            "fluc": 27
          },
          "low": {
            "timestamp": "2026-01-15T22:06:21.293204989Z",
            "fluc": 27
          },
          "nine_am": {
            "timestamp": "0001-01-01T00:00:00Z",
            "fluc": 0
          }
        }
      },
      {
        "entrant_id": "e636e269-a0e9-4ff0-989a-0e5b62563898",
        "market_name": "Final Field",
        "primary_market": true,
        "name": "Next Black Jack",
        "is_scratched": false,
        "gear": "",
        "best_time": "NBT",
        "odds": {
          "fixed_win": 6.5,
          "fixed_place": 1.65
        },
        "scratch_time": 0,
        "barrier": 8,
        "runner_number": 8,
        "prize_money": "12240",
        "age": 1,
        "sex": "D",
        "colour": "BL",
        "silk_colours": "",
        "silk_url_64x64": "",
        "silk_url_128x128": "",
        "form_comment": null,
        "class_level": "",
        "jockey": "",
        "apprentice_indicator": "",
        "allowance_weight": "",
        "owners": "Amber Boody",
        "country": "AUS",
        "trainer_name": "Amber Boody",
        "last_twenty_starts": "6213711743",
        "sire": "AUSSIE INFRARED (AUS)",
        "dam": "ZIP STREAM (AUS)",
        "breeding": "d AUSSIE INFRARED (AUS)-ZIP STREAM (AUS)",
        "weight": {
          "allocated": "",
          "total": ""
        },
        "favourite": false,
        "mover": false,
        "speedmap": {
          "settling_lengths": 6,
          "entrant_id": "e636e269-a0e9-4ff0-989a-0e5b62563898",
          "label": "Midfield"
        },
        "form_indicators": null,
        "past_performances": null,
        "jockey_past_performances": null,
        "trainer_location": "Dalma",
        "meta": null,
        "flucs": [
          6.5
        ],
        "scr_time": null,
        "competitor_id": "",
        "ride_guide_exists": false,
        "ride_guide_thumbnail": "",
        "ride_guide_file": "",
        "flucs_with_timestamp": {
          "last_six": [
            {
              "timestamp": "2026-01-15T22:06:21.293316342Z",
              "fluc": 6.5
            }
          ],
          "open": {
            "timestamp": "2026-01-15T22:06:21.293316342Z",
            "fluc": 6.5
          },
          "high": {
            "timestamp": "2026-01-15T22:06:21.293316342Z",
            "fluc": 6.5
          },
          "low": {
            "timestamp": "2026-01-15T22:06:21.293316342Z",
            "fluc": 6.5
          },
          "nine_am": {
            "timestamp": "0001-01-01T00:00:00Z",
            "fluc": 0
          }
        }
      },
      {
        "entrant_id": "e9da38f0-8453-4732-97ed-b73dc1519b27",
        "market_name": "Final Field",
        "primary_market": true,
        "name": "Jack's Thing",
        "is_scratched": true,
        "gear": "",
        "best_time": "23.43",
        "odds": {
          "fixed_win": 17,
          "fixed_place": 2.6
        },
        "scratch_time": 1768515151,
        "barrier": 0,
        "runner_number": 9,
        "prize_money": "3720",
        "age": 2,
        "sex": "B",
        "colour": "BDL",
        "silk_colours": "",
        "silk_url_64x64": "",
        "silk_url_128x128": "",
        "form_comment": null,
        "class_level": "",
        "jockey": "",
        "apprentice_indicator": "",
        "allowance_weight": "",
        "owners": "Rjd Transport - Mgr R Druery",
        "country": "AUS",
        "trainer_name": "Jean Druery",
        "last_twenty_starts": "6218865847",
        "sire": "JACKSLITTLETHING (AUS)",
        "dam": "JILLIBY CAZ (AUS)",
        "breeding": "b JACKSLITTLETHING (AUS)-JILLIBY CAZ (AUS)",
        "weight": {
          "allocated": "",
          "total": ""
        },
        "favourite": false,
        "mover": false,
        "speedmap": {
          "settling_lengths": 1,
          "entrant_id": "e9da38f0-8453-4732-97ed-b73dc1519b27",
          "label": "Back Marker"
        },
        "form_indicators": null,
        "past_performances": null,
        "jockey_past_performances": null,
        "trainer_location": "Churchable",
        "meta": null,
        "flucs": [
          17
        ],
        "scr_time": "2026-01-15T22:12:31Z",
        "competitor_id": "",
        "ride_guide_exists": false,
        "ride_guide_thumbnail": "",
        "ride_guide_file": "",
        "flucs_with_timestamp": {
          "last_six": [
            {
              "timestamp": "2026-01-15T22:06:21.293231071Z",
              "fluc": 17
            }
          ],
          "open": {
            "timestamp": "2026-01-15T22:06:21.293231071Z",
            "fluc": 17
          },
          "high": {
            "timestamp": "2026-01-15T22:06:21.293231071Z",
            "fluc": 17
          },
          "low": {
            "timestamp": "2026-01-15T22:06:21.293231071Z",
            "fluc": 17
          },
          "nine_am": {
            "timestamp": "0001-01-01T00:00:00Z",
            "fluc": 0
          }
        }
      },
      {
        "entrant_id": "aae6dc3d-e553-4a62-a45e-8a5f2a14ad1d",
        "market_name": "Final Field",
        "primary_market": true,
        "name": "Arnie Ferrari",
        "is_scratched": true,
        "gear": "",
        "best_time": "NBT",
        "odds": {
          "fixed_win": 17,
          "fixed_place": 2.6
        },
        "scratch_time": 1768515151,
        "barrier": 0,
        "runner_number": 10,
        "prize_money": "24170",
        "age": 3,
        "sex": "D",
        "colour": "BDL",
        "silk_colours": "",
        "silk_url_64x64": "",
        "silk_url_128x128": "",
        "form_comment": null,
        "class_level": "",
        "jockey": "",
        "apprentice_indicator": "",
        "allowance_weight": "",
        "owners": "Carlin Wendt",
        "country": "AUS",
        "trainer_name": "Carlin Wendt",
        "last_twenty_starts": "132436x678",
        "sire": "FERNANDO BALE (AUS)",
        "dam": "CASCADE MONELLI (AUS)",
        "breeding": "d FERNANDO BALE (AUS)-CASCADE MONELLI (AUS)",
        "weight": {
          "allocated": "",
          "total": ""
        },
        "favourite": false,
        "mover": false,
        "speedmap": {
          "settling_lengths": 1,
          "entrant_id": "aae6dc3d-e553-4a62-a45e-8a5f2a14ad1d",
          "label": "Back Marker"
        },
        "form_indicators": null,
        "past_performances": null,
        "jockey_past_performances": null,
        "trainer_location": "Postmans Ridge",
        "meta": null,
        "flucs": [
          17
        ],
        "scr_time": "2026-01-15T22:12:31Z",
        "competitor_id": "",
        "ride_guide_exists": false,
        "ride_guide_thumbnail": "",
        "ride_guide_file": "",
        "flucs_with_timestamp": {
          "last_six": [
            {
              "timestamp": "2026-01-15T22:06:21.29321984Z",
              "fluc": 17
            }
          ],
          "open": {
            "timestamp": "2026-01-15T22:06:21.29321984Z",
            "fluc": 17
          },
          "high": {
            "timestamp": "2026-01-15T22:06:21.29321984Z",
            "fluc": 17
          },
          "low": {
            "timestamp": "2026-01-15T22:06:21.29321984Z",
            "fluc": 17
          },
          "nine_am": {
            "timestamp": "0001-01-01T00:00:00Z",
            "fluc": 0
          }
        }
      }
    ],
    "derivatives": null,
    "mover": {
      "entrant_id": "dbe36955-b5c7-40d9-bf26-96f5782b3956",
      "market_name": "Final Field",
      "primary_market": true,
      "name": "Peppimenarti",
      "is_scratched": false,
      "gear": "",
      "best_time": "22.08",
      "odds": {
        "fixed_win": 19,
        "fixed_place": 2.6
      },
      "scratch_time": 0,
      "barrier": 1,
      "runner_number": 1,
      "prize_money": "5150",
      "age": 2,
      "sex": "D",
      "colour": "BL",
      "silk_colours": "",
      "silk_url_64x64": "",
      "silk_url_128x128": "",
      "form_comment": null,
      "class_level": "",
      "jockey": "",
      "apprentice_indicator": "",
      "allowance_weight": "",
      "owners": "Kerry Hoggan",
      "country": "AUS",
      "trainer_name": "Kerry Hoggan",
      "last_twenty_starts": "3633421717",
      "sire": "EQUALIZER (AUS)",
      "dam": "WYNNUM STAR (AUS)",
      "breeding": "d EQUALIZER (AUS)-WYNNUM STAR (AUS)",
      "weight": {
        "allocated": "",
        "total": ""
      },
      "favourite": false,
      "mover": true,
      "speedmap": {
        "settling_lengths": 4,
        "entrant_id": "dbe36955-b5c7-40d9-bf26-96f5782b3956"
      },
      "form_indicators": null,
      "past_performances": null,
      "jockey_past_performances": null,
      "trainer_location": "CHURCHABLE"
    },
    "big_bets": null,
    "live_bets": null,
    "biggest_bet": null,
    "money_tracker": null,
    "error": ""
  }
}